TP2/Display.v
 module Display(
    input wire clk, reset, 
    input wire [1:0] premio_f,
    input wire [4:0] p1_f, p2_f,
    input wire [3:0] state_f,
    output reg [0:6] hex1, hex0, hex2, hex3,
    output reg [0:1] ledp1, ledp2,
    output reg led15,
    output reg sled,
	 output reg [3:0] gled
);

	 
	 parameter zero   = 7'b0000001,
              um     = 7'b1001111,
              dois   = 7'b0010010,
              tres   = 7'b0000110,
              quatro = 7'b1001100,
              cinco  = 7'b0100100,
              seis   = 7'b0100000,
              sete   = 7'b0001111,
              oito   = 7'b0000000,
              nove   = 7'b0000100,
              traco  = 7'b1111110, 
              apagado = 7'b0000000; 
     
    parameter s0 = 4'b0000,
              s1 = 4'b0001,
              s2 = 4'b0010,
              s3 = 4'b0011,
              s4 = 4'b0100,
              sg1 = 4'b0101, // estado de premio 1
              sg2 = 4'b0110, // estado de premio 2
              sg0 = 4'b0111, // estado de premio 0
              sgx = 4'b1000; // estado de espera 
	
	initial begin
        ledp1 = 2'b00;
        ledp2 = 2'b00;
        hex3 = traco;
        hex2 = traco;
        hex0 = traco;
        hex1 = traco;
    end
    
   
    always @(*) begin
        if (reset == 1'b1) begin
            ledp1 = 2'b00;
            ledp2 = 2'b00;
            hex3 = traco;
            hex2 = traco;
            hex0 = traco;
            hex1 = traco;
        end
        case (premio_f)
            2'b01:begin // caso premio 1
                ledp1 = 2'b11; // Os leds designados para acender quando o premio 1 é sorteado
                ledp2 = 2'b00;
                case (p1_f) // Nos diplays, é ligado os segmentos correspondente a quantidade de premios sorteados
                    4'b0000:begin
                        hex1 = zero;
                        hex0 = zero;
                    end
                    4'b0001:begin
                        hex1 = zero;
                        hex0 = um;
                    end
                    4'b0010:begin
                        hex1 = zero;
                        hex0 = dois;
                    end
                    4'b0011:begin
                        hex1 = zero;
                        hex0 = tres;
                    end
                    4'b0100:begin
                        hex1 = zero;
                        hex0 = quatro;
                    end
                    4'b0101:begin
                        hex1 = zero;
                        hex0 = cinco;
                    end
                    4'b0110:begin
                        hex1 = zero;
                        hex0 = seis;
                    end
                    4'b0111:begin
                        hex1 = zero;
                        hex0 = sete;
                    end
                    4'b1000:begin
                        hex1 = zero;
                        hex0 = oito;
                    end
                    4'b1001:begin
                        hex1 = zero;
                        hex0 = nove;
                    end

       
                endcase
            end
            2'b10: begin
                ledp1 = 2'b00; // caso o premio 2 seja sorteado, é aceso
                ledp2 = 2'b11;
                case (p2_f)
                    4'b0000:begin
                        hex3 = zero;
                        hex2 = zero;
                        
                    end
                    4'b0001: begin
                        hex3 = zero;
                        hex2 = um;
                    end
                    4'b0010: begin
                        hex3 = zero;
                        hex2 = dois;
                    end
                    4'b0011: begin
                        hex3 = zero;
                        hex2 = tres;
                    end
                    4'b0100: begin
                        hex3 = zero;
                        hex2 = quatro;
                    end
                    4'b0101: begin
                        hex3 = zero;
                        hex2 = cinco;
                    end
                    4'b0110: begin
                        hex3 = zero;
                        hex2 = seis;
                    end
                    4'b0111: begin
                        hex3 = zero;
                        hex2 = sete;
                    end
                    4'b1000: begin
                        hex3 = zero;
                        hex2 = oito;
                    end
                    4'b1001: begin
                        hex3 = zero;
                        hex2 = nove;
                    end
                    
                endcase
            end
            2'b00: begin
                ledp1 = 2'b00;
                ledp2 = 2'b00;
            end  
        endcase
    end
	 
	always @(state_f) begin // é aceso alguns leds para acompanhar o andamento dos estados na FPGA
			 gled <= state_f;
          if (state_f == s0) begin
            sled <= 1;
          end else begin
            sled <= ~sled;
          end
		  if(state_f == s4)begin
				led15 <= 1;
		  end else begin
				led15 <= 0;
		  end
    end
    
	 
endmodule

TP2/Lot.v
module Lot(clk, num, reset, fim, fim_jogo, insere, premio, p1, p2, state);
  input  clk, reset, fim, insere, fim_jogo; 
  input  [3:0] num;
  output reg [1:0] premio;
  output reg [4:0] p1, p2;
  output reg [3:0] state; // registrador de estados ps; mudei aqui
  reg [3:0] c;   // registrador de consecutivos
  
  // num da loteria: 47019
  /* Codificação dos premios:
		- premio 1 = 01
		- premio 2 = 10
		- s/premio = 00
  */
  parameter s0 = 4'b0000,
    s1  = 4'b0001,
    s2  = 4'b0010,
    s3  = 4'b0011,
    s4  = 4'b0100,
	 sg1 = 4'b0101, // estado de premio 1
	 sg2 = 4'b0110, // estado de premio 2
    sg0 = 4'b0111, // estado de premio 0
	 sgx = 4'b1000; // estado de espera 
					
  
  
  
  initial begin
    state <= s0;
    premio = 2'b00;
    p1 = 5'b00000;
    p2 = 5'b00000;
	 c = 4'b0000;
  end 
  
  always @(posedge clk , posedge reset , posedge fim_jogo , posedge fim) begin
    if (reset == 1'b1) begin
			state <= s0;
			premio <= 2'b00;
			p1 <= 5'b00000;
			p2 <= 5'b00000;
			c <= 4'b0000;
    end else if (fim_jogo == 1'b1) begin
			state <= s0;
			premio <= 2'b00;
			c <= 4'b0000;
    end else if (fim == 1'b1) begin //  depois de comprarar e os numeros de input com os numeros da loteria e gerar o estado de premio, e mostrado a saída e contabilizado o premio
        case(state)
			sg1: begin
				premio = 2'b01;
				p1 <= p1 + 1;
				state <= sgx;
			end
			sg2: begin
				premio = 2'b10;
				p2 <= p2 + 1;
				state <= sgx;
			end
            sg0: begin
                premio = 2'b00;
					 state <= sgx;
            end
				sgx: begin
					premio <= premio;
					state <= state;
				end
			default: begin
				premio = 2'b00;
				state <= state;
			end
		endcase
	 end else if(insere) begin // caso de inserção, onde o numero do input é comparado com os numero da loteria, caso seja iguais, é somado mais 1 no contador de consecutivo e pula para o próximo estado, caso contrario, só pula para o próximo estado;
			case (state)
                s0: begin
                    if(num == 4'b0100)begin
                        c <= c+1;
                        state <= s1;
                    end else if(num != 4'b0100 && num < 4'b1010)begin
                        c <= 0;
                        state <= s1;
                    end else if(num > 4'b1001)begin
								state <= sgx;
					end
						  
                end
                s1: begin
                    if(num == 4'b0111)begin
                        c <= c+1;
                        state <= s2;
                    end else if (num != 4'b0111 && num < 4'b1010) begin
                        c <= 0;
                        state <= s2;                       
                    end else if(num > 4'b1001)begin
								state <= sgx;
					end
                end
                s2: begin
                    if(num == 4'b0000)begin
                        c <= c+1;
                        state <= s3;
                    end else if(num != 4'b0000 && num < 4'b1010)begin
                        if (c >= 2) begin // caso o numero de consecutivo foi maior ou igual a 2, a pessoa tem a chance com o digito 5, por isso mesmo que erre, o contador nao pode zerar;
                            state <= s3;
                        end else if(num > 4'b1001 )begin
									state <= sgx;
					    end else begin
                            c <= 0;
                            state <= s3;
                        end
                        
                    end
                end
                s3: begin
                    if(num == 4'b0001)begin
                        if (c >= 3) begin
                            state <= sg1; // caso acerte os 4 numeros, vai direto para o estado de premio 1;
                        end else begin
                            c <= c +1;
                            state <= s4;  
                        end
                    end else if(num != 4'b0000 && num < 4'b1010)begin
                        if (c >= 2) begin
                            state <= s4;
                        end else if(num > 4'b1001)begin
									 state <= sgx;
					    end else begin
                            c <= 0;
                            state <= s4;
                        end
                    end
                end
                s4: begin
                   case (c) // analisando o contador,
                        2'b10: begin
                            if(insere && (num == 4'b1001))begin // se é dois consecutivos e acerta o digito 5, ganha o premio 2;
                                state <= sg2;
                            end else if(insere && (num != 4'b1001))begin
                                state <= sg0; // caso contrario não ganha nada;
                            end
                        end
                        2'b11: begin
                            if(insere &&(num == 4'b1001))begin // caso acerte 3 consecutivo e o digito 5, ganha o premio 1;
                                state <= sg1;
                            end else if(insere && (num != 4'b1001))begin
                                state <= sg2; // caso erre o 5, fica com 3 consecutivo e ganha o premio 2;
                            end
                        end
						default: begin
                            state <= sg0; 
                        end		
                    endcase 
                end 
            endcase
     end  
  end
endmodule

TP2/Top.v
module Top (
    input wire clk, fim, insere, fim_jogo, reset,
    input wire [3:0] num,
    output wire [0:6] hex0, hex1, hex2, hex3,
    output wire [0:1] ledp1, ledp2,
    output wire led15, sled,
    output wire [3:0] gled,
    output wire [3:0] state
);

    wire [1:0] premio;
    wire [4:0] p1, p2;

    Lot lt(
        .clk(clk), .num(num), .reset(reset),
        .fim(fim), .fim_jogo(fim_jogo),
        .insere(insere), .premio(premio),
        .p1(p1), .p2(p2), .state(state)
    );

    Display ds(
        .hex0(hex0), .hex1(hex1), .hex2(hex2), .hex3(hex3),
        .ledp1(ledp1), .ledp2(ledp2), .led15(led15),
        .premio_f(premio), .p1_f(p1), .p2_f(p2),
        .state_f(state), .sled(sled), .gled(gled), .reset(reset)
    );

endmodule

TP2/lot_tb.v
`timescale 1ns / 1ps

module lot_tb;

  reg clk,reset, fim, insere, fim_jogo;
  reg [3:0] num;
  wire [0:6] hex1, hex0, hex2, hex3;
  wire [0:1] ledp1, ledp2;
  wire led15, sled;
  wire [3:0] state, gled;
  
  
  
  // Instanciação do módulo Top
  Top uut (
    .clk(clk),
    .num(num),
    .reset(reset),
    .fim(fim),
    .fim_jogo(fim_jogo),
    .insere(insere),
    .hex1(hex1),
    .hex0(hex0),
    .hex2(hex2),
    .hex3(hex3),
    .ledp1(ledp1),
    .ledp2(ledp2),
    .led15(led15),
    .state(state),
    .sled(sled),
	 .gled(gled)
  );

 
    /*
    Numeros para teste:
    47010 - premio 1 - 4 consecutivos
    67039 - premio 2 - 2 consequtivos + acerto 5o digito;
    47029 - premio 1 - 3 consequitivos + acerto 5o digito;
    23119 - premio 0 - 1 consequtivo + acerto 5o digito;
    49219 - premio 0 - 2 num, mas não consequtivos + acerto 5o digito;
    17011 - prmeio 0 - 3 consecutivos + erro 5o digito;
    */

  initial begin
    $dumpfile("teste_tp2_gtk.vcd");
	 $dumpvars;
    clk = 0;
    reset = 1;
    insere = 0;
    fim = 0;
    fim_jogo = 0;
    #10
    reset = 0;
    #10

    insere = 1;
    num = 4'b0100; #10 num = 4'b0111; #10 num = 4'b0000; #10 num = 4'b0001; #10 num = 4'b0000; // 47010 
    #10
    insere = 0;
    fim = 1;
    #10
    fim = 0;
    $display("Premio sorteado: %d, Quantidade de P1: %d, Quantidade de P2: %d", uut.premio, uut.p1, uut.p2);
    fim_jogo = 1;
    #10
    fim_jogo = 0;
    #10
    insere = 1;

    num = 4'b0110; #10 num = 4'b0111; #10 num = 4'b0000; #10 num = 4'b0011; #10 num = 4'b1001; // 67039
    #10
    insere = 0;
    #10
    fim = 1;
    #10
    fim = 0;
    $display("Premio sorteado: %d, Quantidade de P1: %d, Quantidade de P2: %d", uut.premio, uut.p1, uut.p2);
    fim_jogo = 1;
    #10

    fim_jogo = 0;
    #10
    insere = 1;
    num = 4'b0100; #10 num = 4'b0111; #10 num = 4'b0000; #10 num = 4'b0010; #10 num = 4'b1001; 
    #10
    insere = 0;
    #10
    fim = 1;
    #10
    fim = 0;
    $display("Premio sorteado: %d, Quantidade de P1: %d, Quantidade de P2: %d", uut.premio, uut.p1, uut.p2);
    fim_jogo = 1;
    #10
    fim_jogo = 0;
    #10

    insere = 1;
    num = 4'b0010; #10 num = 4'b0011; #10 num = 4'b0001; #10 num = 4'b0001; #10 num = 4'b1001; // 49219
    #10
    insere = 0;
    #10
    fim = 1;
    #10
    fim = 0;
    $display("Premio sorteado: %d, Quantidade de P1: %d, Quantidade de P2: %d", uut.premio, uut.p1, uut.p2);
    fim_jogo = 1;
    #10
    fim_jogo = 0;
    #10

    insere = 1;
    num = 4'b0010; #10 num = 4'b0011; #10 num = 4'b0001; #10 num = 4'b0001; #10 num = 4'b1001; // 23119
    #10
    insere = 0;
    #10
    fim = 1;
    #10
    fim = 0;
    $display("Premio sorteado: %d, Quantidade de P1: %d, Quantidade de P2: %d", uut.premio, uut.p1, uut.p2);
    fim_jogo = 1;
    #10
    fim_jogo = 0;
    #10
    
    insere = 1;
    num = 4'b0001; #10 num = 4'b0111; #10 num = 4'b0000; #10 num = 4'b0001; #10 num = 4'b0001; // 17011
    #10
    insere = 0;
    #10
    fim = 1;
    #10
    fim = 0;
    $display("Premio sorteado: %d, Quantidade de P1: %d, Quantidade de P2: %d", uut.premio, uut.p1, uut.p2);
    fim_jogo = 1;
    #10

	  reset = 1;

    $stop;
  end
  always #5 clk = ~clk;

endmodule

TP2/simulation/modelsim/teste_tp2_gtk.vcd
$date
	Thu Dec 07 15:00:16 2023
$end
$version
	ModelSim Version 2020.1
$end
$timescale
	1ps
$end

$scope module lot_tb $end
$var reg 1 ! clk $end
$var reg 1 " reset $end
$var reg 1 # fim $end
$var reg 1 $ insere $end
$var reg 1 % fim_jogo $end
$var reg 4 & num [3:0] $end
$var wire 1 ' hex1 [0] $end
$var wire 1 ( hex1 [1] $end
$var wire 1 ) hex1 [2] $end
$var wire 1 * hex1 [3] $end
$var wire 1 + hex1 [4] $end
$var wire 1 , hex1 [5] $end
$var wire 1 - hex1 [6] $end
$var wire 1 . hex0 [0] $end
$var wire 1 / hex0 [1] $end
$var wire 1 0 hex0 [2] $end
$var wire 1 1 hex0 [3] $end
$var wire 1 2 hex0 [4] $end
$var wire 1 3 hex0 [5] $end
$var wire 1 4 hex0 [6] $end
$var wire 1 5 hex2 [0] $end
$var wire 1 6 hex2 [1] $end
$var wire 1 7 hex2 [2] $end
$var wire 1 8 hex2 [3] $end
$var wire 1 9 hex2 [4] $end
$var wire 1 : hex2 [5] $end
$var wire 1 ; hex2 [6] $end
$var wire 1 < hex3 [0] $end
$var wire 1 = hex3 [1] $end
$var wire 1 > hex3 [2] $end
$var wire 1 ? hex3 [3] $end
$var wire 1 @ hex3 [4] $end
$var wire 1 A hex3 [5] $end
$var wire 1 B hex3 [6] $end
$var wire 1 C ledp1 [0] $end
$var wire 1 D ledp1 [1] $end
$var wire 1 E ledp2 [0] $end
$var wire 1 F ledp2 [1] $end
$var wire 1 G led15 $end
$var wire 1 H sled $end
$var wire 1 I state [3] $end
$var wire 1 J state [2] $end
$var wire 1 K state [1] $end
$var wire 1 L state [0] $end
$var wire 1 M gled [3] $end
$var wire 1 N gled [2] $end
$var wire 1 O gled [1] $end
$var wire 1 P gled [0] $end

$scope module uut $end
$var wire 1 Q clk $end
$var wire 1 R fim $end
$var wire 1 S insere $end
$var wire 1 T fim_jogo $end
$var wire 1 U reset $end
$var wire 1 V num [3] $end
$var wire 1 W num [2] $end
$var wire 1 X num [1] $end
$var wire 1 Y num [0] $end
$var wire 1 . hex0 [0] $end
$var wire 1 / hex0 [1] $end
$var wire 1 0 hex0 [2] $end
$var wire 1 1 hex0 [3] $end
$var wire 1 2 hex0 [4] $end
$var wire 1 3 hex0 [5] $end
$var wire 1 4 hex0 [6] $end
$var wire 1 ' hex1 [0] $end
$var wire 1 ( hex1 [1] $end
$var wire 1 ) hex1 [2] $end
$var wire 1 * hex1 [3] $end
$var wire 1 + hex1 [4] $end
$var wire 1 , hex1 [5] $end
$var wire 1 - hex1 [6] $end
$var wire 1 5 hex2 [0] $end
$var wire 1 6 hex2 [1] $end
$var wire 1 7 hex2 [2] $end
$var wire 1 8 hex2 [3] $end
$var wire 1 9 hex2 [4] $end
$var wire 1 : hex2 [5] $end
$var wire 1 ; hex2 [6] $end
$var wire 1 < hex3 [0] $end
$var wire 1 = hex3 [1] $end
$var wire 1 > hex3 [2] $end
$var wire 1 ? hex3 [3] $end
$var wire 1 @ hex3 [4] $end
$var wire 1 A hex3 [5] $end
$var wire 1 B hex3 [6] $end
$var wire 1 C ledp1 [0] $end
$var wire 1 D ledp1 [1] $end
$var wire 1 E ledp2 [0] $end
$var wire 1 F ledp2 [1] $end
$var wire 1 G led15 $end
$var wire 1 H sled $end
$var wire 1 M gled [3] $end
$var wire 1 N gled [2] $end
$var wire 1 O gled [1] $end
$var wire 1 P gled [0] $end
$var wire 1 I state [3] $end
$var wire 1 J state [2] $end
$var wire 1 K state [1] $end
$var wire 1 L state [0] $end
$var wire 1 Z premio [1] $end
$var wire 1 [ premio [0] $end
$var wire 1 \ p1 [4] $end
$var wire 1 ] p1 [3] $end
$var wire 1 ^ p1 [2] $end
$var wire 1 _ p1 [1] $end
$var wire 1 ` p1 [0] $end
$var wire 1 a p2 [4] $end
$var wire 1 b p2 [3] $end
$var wire 1 c p2 [2] $end
$var wire 1 d p2 [1] $end
$var wire 1 e p2 [0] $end

$scope module lt $end
$var parameter 4 f s0 $end
$var parameter 4 g s1 $end
$var parameter 4 h s2 $end
$var parameter 4 i s3 $end
$var parameter 4 j s4 $end
$var parameter 4 k sg1 $end
$var parameter 4 l sg2 $end
$var parameter 4 m sg0 $end
$var parameter 4 n sgx $end
$var wire 1 Q clk $end
$var wire 1 U reset $end
$var wire 1 R fim $end
$var wire 1 S insere $end
$var wire 1 T fim_jogo $end
$var wire 1 V num [3] $end
$var wire 1 W num [2] $end
$var wire 1 X num [1] $end
$var wire 1 Y num [0] $end
$var reg 2 o premio [1:0] $end
$var reg 5 p p1 [4:0] $end
$var reg 5 q p2 [4:0] $end
$var reg 4 r state [3:0] $end
$var reg 4 s c [3:0] $end
$upscope $end

$scope module ds $end
$var parameter 7 t zero $end
$var parameter 7 u um $end
$var parameter 7 v dois $end
$var parameter 7 w tres $end
$var parameter 7 x quatro $end
$var parameter 7 y cinco $end
$var parameter 7 z seis $end
$var parameter 7 { sete $end
$var parameter 7 | oito $end
$var parameter 7 } nove $end
$var parameter 7 ~ traco $end
$var parameter 7 !! apagado $end
$var parameter 4 "! s0 $end
$var parameter 4 #! s1 $end
$var parameter 4 $! s2 $end
$var parameter 4 %! s3 $end
$var parameter 4 &! s4 $end
$var parameter 4 '! sg1 $end
$var parameter 4 (! sg2 $end
$var parameter 4 )! sg0 $end
$var parameter 4 *! sgx $end
$var wire 1 +! clk $end
$var wire 1 U reset $end
$var wire 1 Z premio_f [1] $end
$var wire 1 [ premio_f [0] $end
$var wire 1 \ p1_f [4] $end
$var wire 1 ] p1_f [3] $end
$var wire 1 ^ p1_f [2] $end
$var wire 1 _ p1_f [1] $end
$var wire 1 ` p1_f [0] $end
$var wire 1 a p2_f [4] $end
$var wire 1 b p2_f [3] $end
$var wire 1 c p2_f [2] $end
$var wire 1 d p2_f [1] $end
$var wire 1 e p2_f [0] $end
$var wire 1 I state_f [3] $end
$var wire 1 J state_f [2] $end
$var wire 1 K state_f [1] $end
$var wire 1 L state_f [0] $end
$var reg 7 ,! hex1 [0:6] $end
$var reg 7 -! hex0 [0:6] $end
$var reg 7 .! hex2 [0:6] $end
$var reg 7 /! hex3 [0:6] $end
$var reg 2 0! ledp1 [0:1] $end
$var reg 2 1! ledp2 [0:1] $end
$var reg 1 2! led15 $end
$var reg 1 3! sled $end
$var reg 4 4! gled [3:0] $end
$upscope $end
$upscope $end
$upscope $end
$enddefinitions $end
#0
$dumpvars
0!
1"
0#
0$
0%
bx &
b0 o
b0 p
b0 q
b0 r
b0 s
b1111110 ,!
b1111110 -!
b1111110 .!
b1111110 /!
b0 0!
b0 1!
02!
13!
b0 4!
b0 f
b1 g
b10 h
b11 i
b100 j
b101 k
b110 l
b111 m
b1000 n
b1 t
b1001111 u
b10010 v
b110 w
b1001100 x
b100100 y
b100000 z
b1111 {
b0 |
b100 }
b1111110 ~
b0 !!
b0 "!
b1 #!
b10 $!
b11 %!
b100 &!
b101 '!
b110 (!
b111 )!
b1000 *!
0-
1,
1+
1*
1)
1(
1'
04
13
12
11
10
1/
1.
0;
1:
19
18
17
16
15
0B
1A
1@
1?
1>
1=
1<
0D
0C
0F
0E
0G
1H
0L
0K
0J
0I
0P
0O
0N
0M
0[
0Z
0`
0_
0^
0]
0\
0e
0d
0c
0b
0a
0S
0T
0R
1U
xY
xX
xW
xV
0Q
z+!
$end
#5000
1!
1Q
#10000
0"
0!
0U
0Q
#15000
1!
1Q
#20000
1$
b100 &
0!
1S
0Y
0X
1W
0V
0Q
#25000
1!
1Q
b1 s
b1 r
1L
b1 4!
03!
1P
0H
#30000
b111 &
0!
1Y
1X
0Q
#35000
1!
1Q
b10 s
b10 r
0L
1K
b10 4!
13!
0P
1O
1H
#40000
b0 &
0!
0Y
0X
0W
0Q
#45000
1!
1Q
b11 s
b11 r
1L
b11 4!
03!
1P
0H
#50000
b1 &
0!
1Y
0Q
#55000
1!
1Q
b101 r
0K
1J
b101 4!
13!
0O
1N
1H
#60000
b0 &
0!
0Y
0Q
#65000
1!
1Q
#70000
0$
1#
0!
0S
1R
0Q
b1 o
1[
b11 0!
b1 ,!
b1 -!
14
03
02
01
00
0/
0.
1-
0,
0+
0*
0)
0(
0'
1D
1C
b1 p
b1000 r
0L
0J
1I
1`
b1001111 -!
13
12
11
1.
b1000 4!
03!
0P
0N
1M
0H
#75000
1!
1Q
#80000
0#
1%
0!
0R
1T
0Q
b0 r
b0 o
b0 s
0[
0I
b0 0!
0D
0C
b0 4!
13!
0M
1H
#85000
1!
1Q
#90000
0%
0!
0T
0Q
#95000
1!
1Q
#100000
1$
b110 &
0!
1S
1X
1W
0Q
#105000
1!
1Q
b1 r
1L
b1 4!
03!
1P
0H
#110000
b111 &
0!
1Y
0Q
#115000
1!
1Q
b1 s
b10 r
0L
1K
b10 4!
13!
0P
1O
1H
#120000
b0 &
0!
0Y
0X
0W
0Q
#125000
1!
1Q
b10 s
b11 r
1L
b11 4!
03!
1P
0H
#130000
b11 &
0!
1Y
1X
0Q
#135000
1!
1Q
b100 r
0L
0K
1J
b100 4!
13!
12!
0P
0O
1N
1H
1G
#140000
b1001 &
0!
0X
1V
0Q
#145000
1!
1Q
b110 r
1K
b110 4!
03!
02!
1O
0H
0G
#150000
0$
0!
0S
0Q
#155000
1!
1Q
#160000
1#
0!
1R
0Q
b10 o
1Z
b11 1!
b1 /!
b1 .!
1;
0:
09
08
07
06
05
1B
0A
0@
0?
0>
0=
0<
1F
1E
b1 q
b1000 r
0K
0J
1I
1e
b1001111 .!
1:
19
18
15
b1000 4!
13!
0O
0N
1M
1H
#165000
1!
1Q
#170000
0#
1%
0!
0R
1T
0Q
b0 r
b0 o
b0 s
0Z
0I
b0 1!
0F
0E
b0 4!
0M
#175000
1!
1Q
#180000
0%
0!
0T
0Q
#185000
1!
1Q
#190000
1$
b100 &
0!
1S
0Y
1W
0V
0Q
#195000
1!
1Q
b1 s
b1 r
1L
b1 4!
03!
1P
0H
#200000
b111 &
0!
1Y
1X
0Q
#205000
1!
1Q
b10 s
b10 r
0L
1K
b10 4!
13!
0P
1O
1H
#210000
b0 &
0!
0Y
0X
0W
0Q
#215000
1!
1Q
b11 s
b11 r
1L
b11 4!
03!
1P
0H
#220000
b10 &
0!
1X
0Q
#225000
1!
1Q
b100 r
0L
0K
1J
b100 4!
13!
12!
0P
0O
1N
1H
1G
#230000
b1001 &
0!
1Y
0X
1V
0Q
#235000
1!
1Q
b101 r
1L
b101 4!
03!
02!
1P
0H
0G
#240000
0$
0!
0S
0Q
#245000
1!
1Q
#250000
1#
0!
1R
0Q
b1 o
1[
b11 0!
1D
1C
b10 p
b1000 r
0L
0J
1I
0`
1_
b10010 -!
04
02
01
10
0.
b1000 4!
13!
0P
0N
1M
1H
#255000
1!
1Q
#260000
0#
1%
0!
0R
1T
0Q
b0 r
b0 o
b0 s
0[
0I
b0 0!
0D
0C
b0 4!
0M
#265000
1!
1Q
#270000
0%
0!
0T
0Q
#275000
1!
1Q
#280000
1$
b10 &
0!
1S
0Y
1X
0V
0Q
#285000
1!
1Q
b1 r
1L
b1 4!
03!
1P
0H
#290000
b11 &
0!
1Y
0Q
#295000
1!
1Q
b10 r
0L
1K
b10 4!
13!
0P
1O
1H
#300000
b1 &
0!
0X
0Q
#305000
1!
1Q
b11 r
1L
b11 4!
03!
1P
0H
#310000
0!
0Q
#315000
1!
1Q
b1 s
b100 r
0L
0K
1J
b100 4!
13!
12!
0P
0O
1N
1H
1G
#320000
b1001 &
0!
1V
0Q
#325000
1!
1Q
b111 r
1L
1K
b111 4!
03!
02!
1P
1O
0H
0G
#330000
0$
0!
0S
0Q
#335000
1!
1Q
#340000
1#
0!
1R
0Q
b1000 r
0L
0K
0J
1I
b1000 4!
13!
0P
0O
0N
1M
1H
#345000
1!
1Q
#350000
0#
1%
0!
0R
1T
0Q
b0 r
b0 s
0I
b0 4!
0M
#355000
1!
1Q
#360000
0%
0!
0T
0Q
#365000
1!
1Q
#370000
1$
b10 &
0!
1S
0Y
1X
0V
0Q
#375000
1!
1Q
b1 r
1L
b1 4!
03!
1P
0H
#380000
b11 &
0!
1Y
0Q
#385000
1!
1Q
b10 r
0L
1K
b10 4!
13!
0P
1O
1H
#390000
b1 &
0!
0X
0Q
#395000
1!
1Q
b11 r
1L
b11 4!
03!
1P
0H
#400000
0!
0Q
#405000
1!
1Q
b1 s
b100 r
0L
0K
1J
b100 4!
13!
12!
0P
0O
1N
1H
1G
#410000
b1001 &
0!
1V
0Q
#415000
1!
1Q
b111 r
1L
1K
b111 4!
03!
02!
1P
1O
0H
0G
#420000
0$
0!
0S
0Q
#425000
1!
1Q
#430000
1#
0!
1R
0Q
b1000 r
0L
0K
0J
1I
b1000 4!
13!
0P
0O
0N
1M
1H
#435000
1!
1Q
#440000
0#
1%
0!
0R
1T
0Q
b0 r
b0 s
0I
b0 4!
0M
#445000
1!
1Q
#450000
0%
0!
0T
0Q
#455000
1!
1Q
#460000
1$
b1 &
0!
1S
0V
0Q
#465000
1!
1Q
b1 r
1L
b1 4!
03!
1P
0H
#470000
b111 &
0!
1X
1W
0Q
#475000
1!
1Q
b1 s
b10 r
0L
1K
b10 4!
13!
0P
1O
1H
#480000
b0 &
0!
0Y
0X
0W
0Q
#485000
1!
1Q
b10 s
b11 r
1L
b11 4!
03!
1P
0H
#490000
b1 &
0!
1Y
0Q
#495000
1!
1Q
b11 s
b100 r
0L
0K
1J
b100 4!
13!
12!
0P
0O
1N
1H
1G
#500000
0!
0Q
#505000
1!
1Q
b111 r
1L
1K
b111 4!
03!
02!
1P
1O
0H
0G
#510000
0$
0!
0S
0Q
#515000
1!
1Q
#520000
1#
0!
1R
0Q
b1000 r
0L
0K
0J
1I
b1000 4!
13!
0P
0O
0N
1M
1H
#525000
1!
1Q
#530000
0#
1%
0!
0R
1T
0Q
b0 r
b0 s
0I
b0 4!
0M
#535000
1!
1Q
#540000
1"
