TP2/Lot.v
module Lot(clk, num, reset, fim, fim_jogo, insere, premio, p1, p2, state);
  input  clk, reset, fim, insere, fim_jogo; 
  input  [0:3] num;
  output reg [0:1] premio;
  output reg [0:4] p1, p2;
  output reg [0:3] state; // registrador de estados ps; mudei aqui
  reg [3:0] c;   // registrador de consecutivos
  
  // num da loteria: 47019
  /* Codificação dos premios:
		- premio 1 = 01
		- premio 2 = 10
		- s/premio = 00
  */
  parameter s0 = 4'b0000,
    s1  = 4'b0001,
    s2  = 4'b0010,
    s3  = 4'b0011,
    s4  = 4'b0100,
	 sg1 = 4'b0101, // estado de premio 1
	 sg2 = 4'b0110, // estado de premio 2
    sg0 = 4'b0111, // estado de premio 0
	 sgx = 4'b1000; // estado de espera 
					
  
  
  
  initial begin
    state <= s0;
    premio = 2'b00;
    p1 = 5'b00000;
    p2 = 5'b00000;
	 c = 4'b0000;
  end 
  
  always @(posedge clk , posedge reset , posedge fim_jogo , posedge fim) begin
    if (reset == 1'b1) begin
			state <= s0;
			premio <= 2'b00;
			p1 <= 5'b00000;
			p2 <= 5'b00000;
			c <= 4'b0000;
    end else if (fim_jogo == 1'b1) begin
			state <= s0;
			premio <= 2'b00;
			c <= 4'b0000;
    end else if (fim == 1'b1) begin //  depois de comprarar e os numeros de input com os numeros da loteria e gerar o estado de premio, e mostrado a saída e contabilizado o premio
        case(state)
			sg1: begin
				premio = 2'b01;
				p1 <= p1 + 1;
				state <= sgx;
			end
			sg2: begin
				premio = 2'b10;
				p2 <= p2 + 1;
				state <= sgx;
			end
            sg0: begin
                premio = 2'b00;
					 state <= sgx;
            end
				sgx: begin
					premio <= premio;
					state <= state;
				end
			default: begin
				premio = 2'b00;
				state <= state;
			end
		endcase
	 end else if(insere) begin // caso de inserção, onde o numero do input é comparado com os numero da loteria, caso seja iguais, é somado mais 1 no contador de consecutivo e pula para o próximo estado, caso contrario, só pula para o próximo estado;
			case (state)
                s0: begin
                    if(num == 4'b0100)begin
                        c <= c+1;
                        state <= s1;
                    end else if(num != 4'b0100 && num < 4'b1010)begin
                        c <= 0;
                        state <= s1;
                    end else if(num > 4'b1001)begin
								state <= sgx;
					end
						  
                end
                s1: begin
                    if(num == 4'b0111)begin
                        c <= c+1;
                        state <= s2;
                    end else if (num != 4'b0111 && num < 4'b1010) begin
                        c <= 0;
                        state <= s2;                       
                    end else if(num > 4'b1001)begin
								state <= sgx;
					end
                end
                s2: begin
                    if(num == 4'b0000)begin
                        c <= c+1;
                        state <= s3;
                    end else if(num != 4'b0000 && num < 4'b1010)begin
                        if (c >= 2) begin // caso o numero de consecutivo foi maior ou igual a 2, a pessoa tem a chance com o digito 5, por isso mesmo que erre, o contador nao pode zerar;
                            state <= s3;
                        end else if(num > 4'b1001 )begin
									state <= sgx;
					    end else begin
                            c <= 0;
                            state <= s3;
                        end
                        
                    end
                end
                s3: begin
                    if(num == 4'b0001)begin
                        if (c >= 3) begin
                            state <= sg1; // caso acerte os 4 numeros, vai direto para o estado de premio 1;
                        end else begin
                            c <= c +1;
                            state <= s4;  
                        end
                    end else if(num != 4'b0000 && num < 4'b1010)begin
                        if (c >= 2) begin
                            state <= s4;
                        end else if(num > 4'b1001)begin
									 state <= sgx;
					    end else begin
                            c <= 0;
                            state <= s4;
                        end
                    end
                end
                s4: begin
                   case (c) // analisando o contador,
                        2'b10: begin
                            if(insere && (num == 4'b1001))begin // se é dois consecutivos e acerta o digito 5, ganha o premio 2;
                                state <= sg2;
                            end else if(insere && (num != 4'b1001))begin
                                state <= sg0; // caso contrario não ganha nada;
                            end
                        end
                        2'b11: begin
                            if(insere &&(num == 4'b1001))begin // caso acerte 3 consecutivo e o digito 5, ganha o premio 1;
                                state <= sg1;
                            end else if(insere && (num != 4'b1001))begin
                                state <= sg2; // caso erre o 5, fica com 3 consecutivo e ganha o premio 2;
                            end
                        end
						default: begin
                            state <= sg0; 
                        end		
                    endcase 
                end 
            endcase
     end  
  end
endmodule

TP2/lot_tb.v
`timescale 1ns/1ps
module lot_tb;
  reg clk_tb, reset_tb, fim_tb, fim_jogo_tb, insere_tb;
  reg [0:3] num_tb;
  wire [0:1] premio_tb;
  wire [0:4] p1_tb, p2_tb;

  Lot TB (.clk(clk_tb), .reset(reset_tb), .fim(fim_tb), .fim_jogo(fim_jogo_tb), .insere(insere_tb),
           .num(num_tb), .premio(premio_tb), .p1(p1_tb), .p2(p2_tb));
  
  initial begin
    $dumpfile("teste_gtx.vcd");
    $dumpvars;

    clk_tb = 0;
    reset_tb = 1;
    fim_tb = 0;
    fim_jogo_tb = 0;
    insere_tb = 0;
    #1;
    reset_tb = 0;
    #1;
    insere_tb = 1;
    num_tb[0] = 0; num_tb[1] = 1; num_tb[2] = 0; num_tb[3] = 0;
	 
	 $display("Numero = %d",num_tb);
    #1;
    num_tb[0] = 0; num_tb[1] = 1; num_tb[2] = 1; num_tb[3] = 1;
	 $display("Numero = %d",num_tb);
    #1;
    num_tb[0] = 0; num_tb[1] = 0; num_tb[2] = 0; num_tb[3] = 0;
	 $display("Numero = %d",num_tb);
    #1;
    num_tb[0] = 0; num_tb[1] = 0; num_tb[2] = 0; num_tb[3] = 1;
	 $display("Numero = %d",num_tb);
    #1;
	 num_tb[0] = 1; num_tb[1] = 0; num_tb[2] = 0; num_tb[3] = 1;
	 $display("Numero = %d",num_tb);
    #1;
    insere_tb = 0;
    fim_tb = 1;
    #1;
	 fim_tb = 0;
	 fim_jogo_tb = 1;
	 #1;
	 fim_jogo_tb = 0;
	 #1;

    $display("Premio sorteado = %d. Quantidade de premio 1 : %d, Quantidade de premio 2: %d", premio_tb, p1_tb, p2_tb);

    #1; 
	 
	 insere_tb = 1;
    num_tb[0] = 1; num_tb[1] = 0; num_tb[2] = 0; num_tb[3] = 0;
	 
	 $display("Numero = %d",num_tb);
    #1;
    num_tb[0] = 1; num_tb[1] = 0; num_tb[2] = 0; num_tb[3] = 1;
	 $display("Numero = %d",num_tb);
    #1;
    num_tb[0] = 0; num_tb[1] = 0; num_tb[2] = 0; num_tb[3] = 0;
	 $display("Numero = %d",num_tb);
    #1;
    num_tb[0] = 0; num_tb[1] = 0; num_tb[2] = 1; num_tb[3] = 0;
	 $display("Numero = %d",num_tb);
    #1;
	 num_tb[0] = 0; num_tb[1] = 0; num_tb[2] = 0; num_tb[3] = 0;
	 $display("Numero = %d",num_tb);
    #1;
    insere_tb = 0;
    fim_tb = 1;
    #1;

    $display("Premio sorteado = %d. Quantidade de premio 1 : %d, Quantidade de premio 2: %d", premio_tb, p1_tb, p2_tb);

    #1; 
			

    $finish; // Adicione um ponto e vírgula aqui
	 
  end
  always #1 clk_tb = ~clk_tb;
endmodule

TP2/simulation/modelsim/teste_gtx.vcd
$date
	Tue Nov 28 22:02:34 2023
$end
$version
	ModelSim Version 2020.1
$end
$timescale
	1ps
$end

$scope module lot_tb $end
$var reg 1 ! clk_tb $end
$var reg 1 " reset_tb $end
$var reg 1 # fim_tb $end
$var reg 1 $ fim_jogo_tb $end
$var reg 1 % insere_tb $end
$var reg 4 & num_tb [0:3] $end
$var wire 1 ' premio_tb [0] $end
$var wire 1 ( premio_tb [1] $end
$var wire 1 ) p1_tb [0] $end
$var wire 1 * p1_tb [1] $end
$var wire 1 + p1_tb [2] $end
$var wire 1 , p1_tb [3] $end
$var wire 1 - p1_tb [4] $end
$var wire 1 . p2_tb [0] $end
$var wire 1 / p2_tb [1] $end
$var wire 1 0 p2_tb [2] $end
$var wire 1 1 p2_tb [3] $end
$var wire 1 2 p2_tb [4] $end

$scope module TB $end
$var parameter 4 3 s0 $end
$var parameter 4 4 s1 $end
$var parameter 4 5 s2 $end
$var parameter 4 6 s3 $end
$var parameter 4 7 s4 $end
$var parameter 4 8 sg1 $end
$var parameter 4 9 sg2 $end
$var parameter 4 : sg0 $end
$var parameter 4 ; sgx $end
$var wire 1 < clk $end
$var wire 1 = reset $end
$var wire 1 > fim $end
$var wire 1 ? insere $end
$var wire 1 @ fim_jogo $end
$var wire 1 A num [0] $end
$var wire 1 B num [1] $end
$var wire 1 C num [2] $end
$var wire 1 D num [3] $end
$var reg 2 E premio [0:1] $end
$var reg 5 F p1 [0:4] $end
$var reg 5 G p2 [0:4] $end
$var reg 4 H state [3:0] $end
$var reg 4 I c [3:0] $end
$upscope $end
$upscope $end
$enddefinitions $end
#0
$dumpvars
0!
1"
0#
0$
0%
bx &
b0 E
b0 F
b0 G
b0 H
b0 I
b0 3
b1 4
b10 5
b11 6
b100 7
b101 8
b110 9
b111 :
b1000 ;
0(
0'
0-
0,
0+
0*
0)
02
01
00
0/
0.
xD
xC
xB
xA
0?
0@
0>
1=
0<
$end
#1000
0"
1!
0=
1<
#2000
1%
b0xxx &
b1xx &
b10x &
b100 &
0!
1?
0D
0C
1B
0A
0<
#3000
b110 &
b111 &
1!
1D
1C
1<
b1 H
#4000
b11 &
b1 &
b0 &
0!
0D
0C
0B
0<
#5000
b1 &
1!
1D
1<
b10 H
#6000
b1001 &
0!
1A
0<
#7000
0%
1#
1!
0?
1>
1<
#8000
0#
1$
0!
0>
1@
0<
b0 H
#9000
0$
1!
0@
1<
#10000
0!
0<
#11000
1%
b1000 &
1!
1?
0D
1<
b1 H
#12000
b1001 &
0!
1D
0<
#13000
b1 &
b0 &
1!
0D
0A
1<
b10 H
#14000
b10 &
0!
1C
0<
#15000
b0 &
1!
0C
1<
b1 I
b11 H
#16000
0%
1#
0!
0?
1>
0<
