Codigos2.0/Codificador.v
/*
Declaração do Modulo
Codificador
*/

module Codificador (A, B, C, D, ready, reset, S0, S1, S2, S3);

  // Definir as entradas de 4 bits:
  input wire A;
  input wire B;
  input wire C;
  input wire D;
  input wire ready;
  input wire reset;

  // Definir as saídas:
  output reg S0;
  output reg S1;
  output reg S2;
  output reg S3;

  always @(posedge ready or posedge reset) begin
    if (reset) begin
      S0 <= 1'bx;
      S1 <= 1'bx;
      S2 <= 1'bx;
      S3 <= 1'bx;
    end else begin
      // Definição das expressões booleanas reduzidas via k-map:
      S0 <= (~A & ~C & D) | (~B & C & ~D) | (B & D) | (A & B & ~C);
      // Função do 1º bit descrita por A'C'D + B'CD' + BD + ABC'

      S1 <= (~A & ~B & ~C) | (~A & ~C & D) | (B & C & ~D) | (A & ~D);
      // Função do 2º bit descrita por A'B'C' + A'C'D + BCD' + AD

      S2 <= (~A & B & D) | (A & ~B & ~C) | (A & C & D) | (A & B & ~D);
      // Função do 3º bit descrita por A'BD + AB'C' + BCD + AB'D

      S3 <= (~A & ~C & ~D) | (~B & ~D) | (~A & B & D) | (A & ~B & ~C);
      // Função do 4º bit descrita por A'C'D' + B'D' + A'BD + AB'C'
    end
  end
endmodule

Codigos2.0/Display.v
module Display (a, b, c, d, ready, reset, dse, dsd);
	input wire a, b, c, d, ready, reset;
	wire s0, s1, s2, s3;
	output reg [0:6] dse;
	output reg [0:6] dsd;
	Codificador en(.A(a), .B(b), .C(c), .D(d), .ready(ready), .reset(reset), .S0(s0), .S1(s1), .S2(s2), .S3(s3));
	
	
	always @(*) begin
		case ({s3, s2, s1, s0})
			4'b0000: begin 
							dsd = 7'b1111110;
							dse = 7'b0000000;
						end
			4'b0001: begin 
							dsd = 7'b0110000;
							dse = 7'b0000000;
						end
			4'b0010: begin 
							dsd = 7'b1101101;
							dse = 7'b0000000;
						end
			4'b0011: begin 
							dsd = 7'b1111001;
							dse = 7'b0000000;
						end
			4'b0100: begin 
							dsd = 7'b0110011;
							dse = 7'b0000000;
						end
			4'b0101: begin 
							dsd = 7'b1011011;
							dse = 7'b0000000;
						end
			4'b0110: begin 
							dsd = 7'b1011111;
							dse = 7'b0000000;
						end
			4'b0111: begin 
							dsd = 7'b1110000;
							dse = 7'b0000000;
						end
			4'b1000: begin 
							dsd = 7'b1111111;
							dse = 7'b0000000;
						end
			4'b1001: begin 
							dsd = 7'b1110011;
							dse = 7'b0000000;
						end
			4'b1010: begin
							dsd = 7'b1111110;
							dse = 7'b0110000;
						end
			4'b1011: begin 
							dsd = 7'b0110000;
							dse = 7'b0110000;
						end
			4'b1100: begin
							dsd = 7'b1101101;
							dse = 7'b0110000;
						end
			4'b1101: begin
							dsd = 7'b1111001;
							dse = 7'b0110000;
						end
			4'b1110: begin 
							dsd = 7'b0110011;
							dse = 7'b0110000;
						end
			4'b1111: begin
							dsd = 7'b1011011;
							dse = 7'b0110000;
						end
			default: begin 
							dsd = 7'b0000000;
							dse = 7'b0000000;
						end
		endcase
	
	end
	

endmodule

Codigos2.0/Tb_display.v
module Tb_display();
	reg a, b, c, d, ready, reset;
	wire [6:0] dse_t, dsd_t;

	Display tb(.a(a), .b(b), .c(c), .d(d), .ready(ready), .reset(reset), .dse(dse_t), .dsd(dsd_t));

	initial begin
		
		$dumpfile("teste_gtk.vcd");
		$dumpvars;
		
		// testando para entrada 0 saida 10
		reset = 1;
		#4;
		reset = 0;
		#4;
		
		a = 1'b0; b = 1'b0; c = 1'b0; d = 1'b0;
		#4;
		ready = 1;
		$display( "Entradas = %b%b%b%b, Saida display esquerdo = %b%b%b%b%b%b%b,Saida display direito = %b%b%b%b%b%b%b",
						a, b, c, d, dse_t[6], dse_t[5], dse_t[4], dse_t[3], dse_t[2], dse_t[1], dse_t[0],
						dsd_t[6],dsd_t[5],dsd_t[4],dsd_t[3],dsd_t[2],dsd_t[1],dsd_t[0]);
		ready = 0;
		
		// testando para entrada 1 saida 3
		reset = 1;
		#4;
		reset = 0;
		#4;
		
		a = 1'b0; b = 1'b0; c = 1'b0; d = 1'b1;
		#4;
		ready = 1;
		$display( "Entradas = %b%b%b%b, Saida display esquerdo = %b%b%b%b%b%b%b,Saida display direito = %b%b%b%b%b%b%b",
						a, b, c, d, dse_t[6], dse_t[5], dse_t[4], dse_t[3], dse_t[2], dse_t[1], dse_t[0],
						dsd_t[6],dsd_t[5],dsd_t[4],dsd_t[3],dsd_t[2],dsd_t[1],dsd_t[0]);
		ready = 0;
		
		// testando para entrada 2 saida 9
		reset = 1;
		#4;
		reset = 0;
		#4;
		
		a = 1'b0; b = 1'b0; c = 1'b1; d = 1'b0;
		#4;
		ready = 1;
		$display( "Entradas = %b%b%b%b, Saida display esquerdo = %b%b%b%b%b%b%b,Saida display direito = %b%b%b%b%b%b%b",
						a, b, c, d, dse_t[6], dse_t[5], dse_t[4], dse_t[3], dse_t[2], dse_t[1], dse_t[0],
						dsd_t[6],dsd_t[5],dsd_t[4],dsd_t[3],dsd_t[2],dsd_t[1],dsd_t[0]);
		ready = 0;
		
		// testando para entrada 3 saida 0
		reset = 1;
		#4;
		reset = 0;
		#4;
		
		a = 1'b0; b = 1'b0; c = 1'b1; d = 1'b1;
		#4;
		ready = 1;
		$display( "Entradas = %b%b%b%b, Saida display esquerdo = %b%b%b%b%b%b%b,Saida display direito = %b%b%b%b%b%b%b",
						a, b, c, d, dse_t[6], dse_t[5], dse_t[4], dse_t[3], dse_t[2], dse_t[1], dse_t[0],
						dsd_t[6],dsd_t[5],dsd_t[4],dsd_t[3],dsd_t[2],dsd_t[1],dsd_t[0]);
		ready = 0;
		
		// testando para entrada 4 saida 8
		reset = 1;
		#4;
		reset = 0;
		#4;
		
		a = 1'b0; b = 1'b1; c = 1'b0; d = 1'b0;
		#4;
		ready = 1;
		$display( "Entradas = %b%b%b%b, Saida display esquerdo = %b%b%b%b%b%b%b,Saida display direito = %b%b%b%b%b%b%b",
						a, b, c, d, dse_t[6], dse_t[5], dse_t[4], dse_t[3], dse_t[2], dse_t[1], dse_t[0],
						dsd_t[6],dsd_t[5],dsd_t[4],dsd_t[3],dsd_t[2],dsd_t[1],dsd_t[0]);
		ready = 0;
		
		// testando para entrada 5 saida 15
		reset = 1;
		#4;
		reset = 0;
		#4;
		
		a = 1'b0; b = 1'b1; c = 1'b0; d = 1'b1;
		#4;
		ready = 1;
		$display( "Entradas = %b%b%b%b, Saida display esquerdo = %b%b%b%b%b%b%b,Saida display direito = %b%b%b%b%b%b%b",
						a, b, c, d, dse_t[6], dse_t[5], dse_t[4], dse_t[3], dse_t[2], dse_t[1], dse_t[0],
						dsd_t[6],dsd_t[5],dsd_t[4],dsd_t[3],dsd_t[2],dsd_t[1],dsd_t[0]);
		ready = 0;
		
		// testando para entrada 6 saida 2
		reset = 1;
		#4;
		reset = 0;
		#4;
		
		a = 1'b0; b = 1'b1; c = 1'b1; d = 1'b0;
		#4;
		ready = 1;
		$display( "Entradas = %b%b%b%b, Saida display esquerdo = %b%b%b%b%b%b%b,Saida display direito = %b%b%b%b%b%b%b",
						a, b, c, d, dse_t[6], dse_t[5], dse_t[4], dse_t[3], dse_t[2], dse_t[1], dse_t[0],
						dsd_t[6],dsd_t[5],dsd_t[4],dsd_t[3],dsd_t[2],dsd_t[1],dsd_t[0]);
		ready = 0;
		
		// testando para entrada 7 saida 13
		reset = 1;
		#4;
		reset = 0;
		#4;
		
		a = 1'b0; b = 1'b1; c = 1'b1; d = 1'b1;
		#4;
		ready = 1;
		$display( "Entradas = %b%b%b%b, Saida display esquerdo = %b%b%b%b%b%b%b,Saida display direito = %b%b%b%b%b%b%b",
						a, b, c, d, dse_t[6], dse_t[5], dse_t[4], dse_t[3], dse_t[2], dse_t[1], dse_t[0],
						dsd_t[6],dsd_t[5],dsd_t[4],dsd_t[3],dsd_t[2],dsd_t[1],dsd_t[0]);
		ready = 0;
		
		// testando para entrada 8 saida 14
		reset = 1;
		#4;
		reset = 0;
		#4;
		
		a = 1'b1; b = 1'b0; c = 1'b0; d = 1'b0;
		#4;
		ready = 1;
		$display( "Entradas = %b%b%b%b, Saida display esquerdo = %b%b%b%b%b%b%b,Saida display direito = %b%b%b%b%b%b%b",
						a, b, c, d, dse_t[6], dse_t[5], dse_t[4], dse_t[3], dse_t[2], dse_t[1], dse_t[0],
						dsd_t[6],dsd_t[5],dsd_t[4],dsd_t[3],dsd_t[2],dsd_t[1],dsd_t[0]);
		ready = 0;
		
		
		// testando para entrada 9 saida 12
		reset = 1;
		#4;
		reset = 0;
		#4;
		
		a = 1'b1; b = 1'b0; c = 1'b0; d = 1'b1;
		#4;
		ready = 1;
		$display( "Entradas = %b%b%b%b, Saida display esquerdo = %b%b%b%b%b%b%b,Saida display direito = %b%b%b%b%b%b%b",
						a, b, c, d, dse_t[6], dse_t[5], dse_t[4], dse_t[3], dse_t[2], dse_t[1], dse_t[0],
						dsd_t[6],dsd_t[5],dsd_t[4],dsd_t[3],dsd_t[2],dsd_t[1],dsd_t[0]);
		ready = 0;
		
		// testando para entrada 10 saida 11
		reset = 1;
		#4;
		reset = 0;
		#4;
		
		a = 1'b1; b = 1'b0; c = 1'b1; d = 1'b0;
		#4;
		ready = 1;
		$display( "Entradas = %b%b%b%b, Saida display esquerdo = %b%b%b%b%b%b%b,Saida display direito = %b%b%b%b%b%b%b",
						a, b, c, d, dse_t[6], dse_t[5], dse_t[4], dse_t[3], dse_t[2], dse_t[1], dse_t[0],
						dsd_t[6],dsd_t[5],dsd_t[4],dsd_t[3],dsd_t[2],dsd_t[1],dsd_t[0]);
		ready = 0;
		
		// testando para entrada 11 saida 4
		reset = 1;
		#4;
		reset = 0;
		#4;
		
		a = 1'b1; b = 1'b0; c = 1'b1; d = 1'b1;
		#4;
		ready = 1;
		$display( "Entradas = %b%b%b%b, Saida display esquerdo = %b%b%b%b%b%b%b,Saida display direito = %b%b%b%b%b%b%b",
						a, b, c, d, dse_t[6], dse_t[5], dse_t[4], dse_t[3], dse_t[2], dse_t[1], dse_t[0],
						dsd_t[6],dsd_t[5],dsd_t[4],dsd_t[3],dsd_t[2],dsd_t[1],dsd_t[0]);
		ready = 0;
		
		
		
		// testando para entrada 12 saida 7
		reset = 1;
		#4;
		reset = 0;
		#4;
		
		a = 1'b1; b = 1'b1; c = 1'b0; d = 1'b0;
		#4;
		ready = 1;
		$display( "Entradas = %b%b%b%b, Saida display esquerdo = %b%b%b%b%b%b%b,Saida display direito = %b%b%b%b%b%b%b",
						a, b, c, d, dse_t[6], dse_t[5], dse_t[4], dse_t[3], dse_t[2], dse_t[1], dse_t[0],
						dsd_t[6],dsd_t[5],dsd_t[4],dsd_t[3],dsd_t[2],dsd_t[1],dsd_t[0]);
		ready = 0;
		
		// testando para entrada 13 saida 1
		reset = 1;
		#4;
		reset = 0;
		#4;
		
		a = 1'b1; b = 1'b1; c = 1'b0; d = 1'b1;
		#4;
		ready = 1;
		$display( "Entradas = %b%b%b%b, Saida display esquerdo = %b%b%b%b%b%b%b,Saida display direito = %b%b%b%b%b%b%b",
						a, b, c, d, dse_t[6], dse_t[5], dse_t[4], dse_t[3], dse_t[2], dse_t[1], dse_t[0],
						dsd_t[6],dsd_t[5],dsd_t[4],dsd_t[3],dsd_t[2],dsd_t[1],dsd_t[0]);
		ready = 0;
		
		// testando para entrada 14 saida 6
		reset = 1;
		#4;
		reset = 0;
		#4;
		
		a = 1'b1; b = 1'b1; c = 1'b1; d = 1'b0;
		#4;
		ready = 1;
		$display( "Entradas = %b%b%b%b, Saida display esquerdo = %b%b%b%b%b%b%b,Saida display direito = %b%b%b%b%b%b%b",
						a, b, c, d, dse_t[6], dse_t[5], dse_t[4], dse_t[3], dse_t[2], dse_t[1], dse_t[0],
						dsd_t[6],dsd_t[5],dsd_t[4],dsd_t[3],dsd_t[2],dsd_t[1],dsd_t[0]);
		ready = 0;
		
		// testando para entrada 15 saida 5
		reset = 1;
		#4;
		reset = 0;
		#4;
		
		a = 1'b1; b = 1'b1; c = 1'b1; d = 1'b1;
		#4;
		ready = 1;
		$display( "Entradas = %b%b%b%b, Saida display esquerdo = %b%b%b%b%b%b%b,Saida display direito = %b%b%b%b%b%b%b",
						a, b, c, d, dse_t[6], dse_t[5], dse_t[4], dse_t[3], dse_t[2], dse_t[1], dse_t[0],
						dsd_t[6],dsd_t[5],dsd_t[4],dsd_t[3],dsd_t[2],dsd_t[1],dsd_t[0]);
		
		ready = 0;
		$stop;
	end
endmodule

Codigos2.0/simulation/modelsim/teste_gtk.vcd
$date
	Tue Oct 24 21:52:24 2023
$end
$version
	ModelSim Version 2020.1
$end
$timescale
	1ps
$end

$scope module Tb_display $end
$var reg 1 ! a $end
$var reg 1 " b $end
$var reg 1 # c $end
$var reg 1 $ d $end
$var reg 1 % ready $end
$var reg 1 & reset $end
$var wire 1 ' dse_t [6] $end
$var wire 1 ( dse_t [5] $end
$var wire 1 ) dse_t [4] $end
$var wire 1 * dse_t [3] $end
$var wire 1 + dse_t [2] $end
$var wire 1 , dse_t [1] $end
$var wire 1 - dse_t [0] $end
$var wire 1 . dsd_t [6] $end
$var wire 1 / dsd_t [5] $end
$var wire 1 0 dsd_t [4] $end
$var wire 1 1 dsd_t [3] $end
$var wire 1 2 dsd_t [2] $end
$var wire 1 3 dsd_t [1] $end
$var wire 1 4 dsd_t [0] $end

$scope module tb $end
$var wire 1 5 a $end
$var wire 1 6 b $end
$var wire 1 7 c $end
$var wire 1 8 d $end
$var wire 1 9 ready $end
$var wire 1 : reset $end
$var wire 1 ; s0 $end
$var wire 1 < s1 $end
$var wire 1 = s2 $end
$var wire 1 > s3 $end
$var reg 7 ? dse [0:6] $end
$var reg 7 @ dsd [0:6] $end

$scope module en $end
$var wire 1 5 A $end
$var wire 1 6 B $end
$var wire 1 7 C $end
$var wire 1 8 D $end
$var wire 1 9 ready $end
$var wire 1 : reset $end
$var wire 1 ; S0 $end
$var wire 1 < S1 $end
$var wire 1 = S2 $end
$var wire 1 > S3 $end
$upscope $end
$upscope $end
$upscope $end
$enddefinitions $end
#0
$dumpvars
x!
x"
x#
x$
x%
1&
bx ?
bx @
x-
x,
x+
x*
x)
x(
x'
x4
x3
x2
x1
x0
x/
x.
x;
x<
x=
x>
1:
x9
x8
x7
x6
x5
$end
#4
0&
0:
#8
0!
0"
0#
0$
05
06
07
08
0=
1<
1>
0;
b1111110 @
b110000 ?
0-
0,
0+
0*
1)
1(
0'
04
13
12
11
10
1/
1.
#12
1%
0%
1&
09
1:
#16
0&
0:
#20
1$
18
0>
1;
b1111001 @
b0 ?
0)
0(
14
03
02
#24
1%
0%
1&
1:
#28
0&
0:
#32
1#
0$
17
08
0<
1>
b1110011 @
13
01
#36
1%
0%
1&
1:
#40
0&
0:
#44
1$
18
0>
0;
b1111110 @
04
12
11
#48
1%
0%
1&
1:
#52
0&
0:
#56
1"
0#
0$
16
07
08
1>
b1111111 @
14
#60
1%
0%
1&
1:
#64
0&
0:
#68
1$
18
1=
1<
1;
b1011011 @
b110000 ?
1)
1(
02
0/
#72
1%
0%
1&
1:
#76
0&
0:
#80
1#
0$
17
08
0>
0=
0;
b1101101 @
b0 ?
0)
0(
03
12
00
1/
#84
1%
0%
1&
1:
#88
0&
0:
#92
1$
18
1>
1=
0<
1;
b1111001 @
b110000 ?
1)
1(
02
10
#96
1%
0%
1&
1:
#100
0&
0:
#104
1!
0"
0#
0$
15
06
07
08
0;
1<
b110011 @
13
01
0.
#108
1%
0%
1&
1:
#112
0&
0:
#116
1$
18
0<
b1101101 @
03
12
11
00
1.
#120
1%
0%
1&
1:
#124
0&
0:
#128
1#
0$
17
08
0=
1<
1;
b110000 @
04
02
01
10
0.
#132
1%
0%
1&
1:
#136
0&
0:
#140
1$
18
0>
1=
0<
0;
b110011 @
b0 ?
0)
0(
14
13
#144
1%
0%
1&
1:
#148
0&
0:
#152
1"
0#
0$
16
07
08
1;
1<
b1110000 @
04
03
1.
#156
1%
0%
1&
1:
#160
0&
0:
#164
1$
18
0=
0<
b110000 @
0.
#168
1%
0%
1&
1:
#172
0&
0:
#176
1#
0$
17
08
1=
1<
0;
b1011111 @
14
13
12
11
0/
1.
#180
1%
0%
1&
1:
#184
0&
0:
#188
1$
18
0<
1;
b1011011 @
02
#192
1%
0%
