Codigos2.0/Codificador.v
/*
Declaração do Modulo
encode
*/
module Codificador(A, B, C, D, ready, reset, S0, S1, S2, S3);

  // Definir as entradas de 4 bits:
  input wire A;
  input wire B;
  input wire C;
  input wire D;
  input wire ready;
  input wire reset;

  // Definir as saídas:
  output wire S0;
  output wire S1;
  output wire S2;
  output wire S3;

      // Definição das expressões booleanas reduzidas via k-map:
      assign S0 = (~A & ~C & D) | (~B & C & ~D) | (B & D) | (A & B & ~C);
      // Função do 1º bit descrita por A'C'D + B'CD' + BD + ABC'

      assign S1 = (~A & ~B & ~C) | (~A & ~C & D) | (B & C & ~D) | (A & ~D);
      // Função do 2º bit descrita por A'B'C' + A'C'D + BCD' + AD

      assign S2 = (~A & B & D) | (A & ~B & ~C) | (A & C & D) | (A & B & ~D);
      // Função do 3º bit descrita por A'BD + AB'C' + BCD + AB'D

     assign S3 = (~A & ~C & ~D) | (~B & ~D) | (~A & B & D) | (A & ~B & ~C);
      // Função do 4º bit descrita por A'C'D' + B'D' + A'BD + AB'C'

endmodule

Codigos2.0/TestBench.v
`timescale 1ns/100ps

module TestBench();
	 reg a, b, c, d, ready, reset;
    wire s0, s1, s2, s3;
    
    Codificador en(.A(a), .B(b), .C(c), .D(d), .ready(ready), .reset(reset), .S0(s0), .S1(s1), .S2(s2), .S3(s3));

	initial begin
			$dumpfile("teste_gtk.vcd");
			$dumpvars;
		
        // Testando para cada numero
	    // 0;
        reset = 1;
        #4; 

        reset = 0;
        #4; 
        a = 1'b0; b = 1'b0; c = 1'b0; d = 1'b0;
        $display("Time = %0t | Entrada = %0d%0d%0d%0d Saída = %0d%0d%0d%0d",
             $time, a, b, c, d, s0, s1, s2, s3);

        // 1;
        #4; ready = 1;
        #4; ready = 0;
        #4; 
        a = 1'b0; b = 1'b0; c = 1'b0; d = 1'b1;
        $display("Time = %0t | Entrada = %0d%0d%0d%0d Saída = %0d%0d%0d%0d",
             $time, a, b, c, d, s0, s1, s2, s3);

        // 2;
        #4; ready = 1;
        #4; ready = 0;
        #4; 
        a = 1'b0;
        b = 1'b0;
        c = 1'b1;
        d = 1'b0;
        $display("Time = %0t | Entrada = %0d%0d%0d%0d Saída = %0d%0d%0d%0d",
             $time, a, b, c, d, s0, s1, s2, s3);

        // 3;
		#4;
		reset = 1;
		ready = 0;
		#4;
		a = 1'b0; b = 1'b0; c = 1'b1; d = 1'b1;
        $display("Time = %0t | Entrada = %0d%0d%0d%0d Saída = %0d%0d%0d%0d",
             $time, a, b, c, d, s0, s1, s2, s3);

        // 4;
		#4;
		reset = 1;
		ready = 0;
		#4;
		a = 1'b0; b = 1'b1; c = 1'b0; d = 1'b0;
        $display("Time = %0t | Entrada = %0d%0d%0d%0d Saída = %0d%0d%0d%0d",
             $time, a, b, c, d, s0, s1, s2, s3);

        //5
        #4;
		reset = 1;
		ready = 0;
		#4;
        a = 1'b0; b = 1'b1; c = 1'b0; d = 1'b1;
        $display("Time = %0t | Entrada = %0d%0d%0d%0d Saída = %0d%0d%0d%0d",
             $time, a, b, c, d, s0, s1, s2, s3);

        //6
        #4;
		reset = 1;
		ready = 0;
		#4;
        a = 1'b0; b = 1'b1; c = 1'b1; d = 1'b0;
        $display("Time = %0t | Entrada = %0d%0d%0d%0d Saída = %0d%0d%0d%0d",
             $time, a, b, c, d, s0, s1, s2, s3);

        //7
        #4;
		reset = 1;
		ready = 0;
		#4;
        a = 1'b0; b = 1'b1; c = 1'b1; d = 1'b1;
        $display("Time = %0t | Entrada = %0d%0d%0d%0d Saída = %0d%0d%0d%0d",
             $time, a, b, c, d, s0, s1, s2, s3);

        //8
        #4;
		reset = 1;
		ready = 0;
		#4;
        a = 1'b1; b = 1'b0; c = 1'b0; d = 1'b0;
        $display("Time = %0t | Entrada = %0d%0d%0d%0d Saída = %0d%0d%0d%0d",
             $time, a, b, c, d, s0, s1, s2, s3);

        //9
        #4;
		reset = 1;
		ready = 0;
		#4;
        a = 1'b1; b = 1'b0; c = 1'b0; d = 1'b1;
        $display("Time = %0t | Entrada = %0d%0d%0d%0d Saída = %0d%0d%0d%0d",
             $time, a, b, c, d, s0, s1, s2, s3);

        //10
        #4;
		reset = 1;
		ready = 0;
		#4;
        a = 1'b1; b = 1'b0; c = 1'b1; d = 1'b0;
        $display("Time = %0t | Entrada = %0d%0d%0d%0d Saída = %0d%0d%0d%0d",
             $time, a, b, c, d, s0, s1, s2, s3);

        //11
        #4;
		reset = 1;
		ready = 0;
		#4;
        a = 1'b1; b = 1'b0; c = 1'b1; d = 1'b1;
        $display("Time = %0t | Entrada = %0d%0d%0d%0d Saída = %0d%0d%0d%0d",
             $time, a, b, c, d, s0, s1, s2, s3);

        //12
        #4;
		reset = 1;
		ready = 0;
		#4;
        a = 1'b1; b = 1'b1; c = 1'b0; d = 1'b0;
        $display("Time = %0t | Entrada = %0d%0d%0d%0d Saída = %0d%0d%0d%0d",
             $time, a, b, c, d, s0, s1, s2, s3);

        //13
        #4;
		reset = 1;
		ready = 0;
		#4;
        a = 1'b1; b = 1'b1; c = 1'b0; d = 1'b1;
        $display("Time = %0t | Entrada = %0d%0d%0d%0d Saída = %0d%0d%0d%0d",
             $time, a, b, c, d, s0, s1, s2, s3);

        //14
        #4;
		reset = 1;
		ready = 0;
		#4;
        a = 1'b1; b = 1'b1; c = 1'b1; d = 1'b0;

        $display("Time = %0t | Entrada = %0d%0d%0d%0d Saída = %0d%0d%0d%0d",
             $time, a, b, c, d, s0, s1, s2, s3);

        //15
        #4;
		reset = 1;
		ready = 0;
		#4;
        a = 1'b1; b = 1'b1; c = 1'b1; d = 1'b1;

        $display("Time = %0t | Entrada = %0d%0d%0d%0d Saída = %0d%0d%0d%0d",
             $time, a, b, c, d, s0, s1, s2, s3);

		// Finalizar a simulação
		$stop;
	end
endmodule

Codigos2.0/simulation/modelsim/teste_gtk.vcd
$date
	Mon Oct 23 10:43:10 2023
$end
$version
	ModelSim Version 2020.1
$end
$timescale
	1ps
$end

$scope module TestBench $end
$var reg 1 ! a $end
$var reg 1 " b $end
$var reg 1 # c $end
$var reg 1 $ d $end
$var reg 1 % ready $end
$var reg 1 & reset $end
$var wire 1 ' s0 $end
$var wire 1 ( s1 $end
$var wire 1 ) s2 $end
$var wire 1 * s3 $end

$scope module en $end
$var wire 1 + A $end
$var wire 1 , B $end
$var wire 1 - C $end
$var wire 1 . D $end
$var wire 1 / ready $end
$var wire 1 0 reset $end
$var wire 1 ' S0 $end
$var wire 1 ( S1 $end
$var wire 1 ) S2 $end
$var wire 1 * S3 $end
$upscope $end
$upscope $end
$enddefinitions $end
#0
$dumpvars
x!
x"
x#
x$
x%
1&
x'
x(
x)
x*
10
x/
x.
x-
x,
x+
$end
#4000
0&
00
#8000
0!
0"
0#
0$
0+
0,
0-
0.
0'
1*
1(
0)
#12000
1%
1/
#16000
0%
0/
#20000
1$
1.
1'
0*
#24000
1%
1/
#28000
0%
0/
#32000
1#
0$
1-
0.
1*
0(
#36000
1&
10
#40000
1$
1.
0'
0*
#48000
1"
0#
0$
1,
0-
0.
1*
#56000
1$
1.
1'
1(
1)
#64000
1#
0$
1-
0.
0'
0)
0*
#72000
1$
1.
1'
0(
1)
1*
#80000
1!
0"
0#
0$
1+
0,
0-
0.
1(
0'
#88000
1$
1.
0(
#96000
1#
0$
1-
0.
1'
1(
0)
#104000
1$
1.
0'
0(
1)
0*
#112000
1"
0#
0$
1,
0-
0.
1(
1'
#120000
1$
1.
0(
0)
#128000
1#
0$
1-
0.
0'
1(
1)
#136000
1$
