TP1/Códigos/Codificador.v
module Codificador(A, B, C, D, Ready, Reset, S0, S1, S2, S3 );
  // entradas dos bits e os acionadores ready e reset. 
  input wire A, B, C, D, Ready, Reset;
  output wire S0, S1, S2, S3;
	// saídas codificada conforme documentação de orientação do TP. 
  //Definindos as saídas por meio de equações boleanas
  assign S0 = (~A & ~C & D & Ready) | (~B & C & ~D & Ready) | (B & D & Ready) | (A & B & ~C & Ready) | Reset;
 

  assign S1 = (~B & ~C & ~D & Ready) | (~A & ~C & D & Ready) | (B & C & ~D & Ready) | (A & ~D & Ready) | Reset;
  

  assign S2 = (~A & B & D & Ready) | (A & ~B & ~C & Ready) | (A & C & D & Ready) | (A & B & ~D & Ready) | Reset;
 

  assign S3 = (~A & ~C & ~D & Ready) | (~B & ~D & Ready) | (~A & B & D & Ready) | (A & ~B & ~C & Ready) | Reset;
 

endmodule

Codigos2.0/Display.v
module Display (a, b, c, d, ready, reset, dse, dsd);
	input wire a, b, c, d, ready, reset;
	wire s0, s1, s2, s3;
	output reg [0:6] dse;
	output reg [0:6] dsd;
	Codificador en(.A(a), .B(b), .C(c), .D(d), .ready(ready), .reset(reset), .S0(s0), .S1(s1), .S2(s2), .S3(s3));
	
	
	always @(*) begin
		case ({s3, s2, s1, s0})
			4'b0000: begin 
							dsd = 7'b1111110;
							dse = 7'b0000000;
						end
			4'b0001: begin 
							dsd = 7'b0110000;
							dse = 7'b0000000;
						end
			4'b0010: begin 
							dsd = 7'b1101101;
							dse = 7'b0000000;
						end
			4'b0011: begin 
							dsd = 7'b1111001;
							dse = 7'b0000000;
						end
			4'b0100: begin 
							dsd = 7'b0110011;
							dse = 7'b0000000;
						end
			4'b0101: begin 
							dsd = 7'b1011011;
							dse = 7'b0000000;
						end
			4'b0110: begin 
							dsd = 7'b1011111;
							dse = 7'b0000000;
						end
			4'b0111: begin 
							dsd = 7'b1110000;
							dse = 7'b0000000;
						end
			4'b1000: begin 
							dsd = 7'b1111111;
							dse = 7'b0000000;
						end
			4'b1001: begin 
							dsd = 7'b1110011;
							dse = 7'b0000000;
						end
			4'b1010: begin
							dsd = 7'b1111110;
							dse = 7'b0110000;
						end
			4'b1011: begin 
							dsd = 7'b0110000;
							dse = 7'b0110000;
						end
			4'b1100: begin
							dsd = 7'b1101101;
							dse = 7'b0110000;
						end
			4'b1101: begin
							dsd = 7'b1111001;
							dse = 7'b0110000;
						end
			4'b1110: begin 
							dsd = 7'b0110011;
							dse = 7'b0110000;
						end
			4'b1111: begin
							dsd = 7'b1011011;
							dse = 7'b0110000;
						end
			default: begin 
							dsd = 7'b0000000;
							dse = 7'b0000000;
						end
		endcase
	
	end
	

endmodule

TP1/Códigos/TestBench.v
`timescale 1ns/10ps

module TestBench();
	reg a, b, c, d, ready, reset;
	wire [6:0] dse_t, dsd_t;
	
	Display tb(.a(a), .b(b), .c(c), .d(d), .ready(ready), .reset(reset), .dse(dse_t), .dsd(dsd_t));

	initial begin
		
		$dumpfile("teste_gtk.vcd");
		$dumpvars;
		
		// testando para entrada 0 saida 10
		reset = 1;
		ready = 1;
		#10;
		reset = 0;
		#10;
		
		a = 1'b0; b = 1'b0; c = 1'b0; d = 1'b0;
		#10;
		ready = 1;
		$display( "Entradas = %b%b%b%b, Saida display esquerdo = %b%b%b%b%b%b%b,Saida display direito = %b%b%b%b%b%b%b",
						a, b, c, d, dse_t[6], dse_t[5], dse_t[4], dse_t[3], dse_t[2], dse_t[1], dse_t[0],
						dsd_t[6],dsd_t[5],dsd_t[4],dsd_t[3],dsd_t[2],dsd_t[1],dsd_t[0]);
	
		#10;
		// testando para entrada 1 saida 3
		reset = 1;
		#10;
		reset = 0;
		#4;
		
		a = 1'b0; b = 1'b0; c = 1'b0; d = 1'b1;
		#4;

		$display( "Entradas = %b%b%b%b, Saida display esquerdo = %b%b%b%b%b%b%b,Saida display direito = %b%b%b%b%b%b%b",
						a, b, c, d, dse_t[6], dse_t[5], dse_t[4], dse_t[3], dse_t[2], dse_t[1], dse_t[0],
						dsd_t[6],dsd_t[5],dsd_t[4],dsd_t[3],dsd_t[2],dsd_t[1],dsd_t[0]);
	
		
		// testando para entrada 2 saida 9
		reset = 1;
		#4;
		reset = 0;
		#4;
		
		a = 1'b0; b = 1'b0; c = 1'b1; d = 1'b0;
		#4;

		$display( "Entradas = %b%b%b%b, Saida display esquerdo = %b%b%b%b%b%b%b,Saida display direito = %b%b%b%b%b%b%b",
						a, b, c, d, dse_t[6], dse_t[5], dse_t[4], dse_t[3], dse_t[2], dse_t[1], dse_t[0],
						dsd_t[6],dsd_t[5],dsd_t[4],dsd_t[3],dsd_t[2],dsd_t[1],dsd_t[0]);

		
		// testando para entrada 3 saida 0
		reset = 1;
		#4;
		reset = 0;
		#4;
		
		a = 1'b0; b = 1'b0; c = 1'b1; d = 1'b1;
		#4;
		$display( "Entradas = %b%b%b%b, Saida display esquerdo = %b%b%b%b%b%b%b,Saida display direito = %b%b%b%b%b%b%b",
						a, b, c, d, dse_t[6], dse_t[5], dse_t[4], dse_t[3], dse_t[2], dse_t[1], dse_t[0],
						dsd_t[6],dsd_t[5],dsd_t[4],dsd_t[3],dsd_t[2],dsd_t[1],dsd_t[0]);

		
		// testando para entrada 4 saida 8
		reset = 1;
		#4;
		reset = 0;
		#4;
		
		a = 1'b0; b = 1'b1; c = 1'b0; d = 1'b0;
		#4;

		$display( "Entradas = %b%b%b%b, Saida display esquerdo = %b%b%b%b%b%b%b,Saida display direito = %b%b%b%b%b%b%b",
						a, b, c, d, dse_t[6], dse_t[5], dse_t[4], dse_t[3], dse_t[2], dse_t[1], dse_t[0],
						dsd_t[6],dsd_t[5],dsd_t[4],dsd_t[3],dsd_t[2],dsd_t[1],dsd_t[0]);

		// testando para entrada 5 saida 15
		reset = 1;
		#4;
		reset = 0;
		#4;
		
		a = 1'b0; b = 1'b1; c = 1'b0; d = 1'b1;
		#4;

		$display( "Entradas = %b%b%b%b, Saida display esquerdo = %b%b%b%b%b%b%b,Saida display direito = %b%b%b%b%b%b%b",
						a, b, c, d, dse_t[6], dse_t[5], dse_t[4], dse_t[3], dse_t[2], dse_t[1], dse_t[0],
						dsd_t[6],dsd_t[5],dsd_t[4],dsd_t[3],dsd_t[2],dsd_t[1],dsd_t[0]);

		
		// testando para entrada 6 saida 2
		reset = 1;
		#4;
		reset = 0;
		#4;
		
		a = 1'b0; b = 1'b1; c = 1'b1; d = 1'b0;
		#4;

		$display( "Entradas = %b%b%b%b, Saida display esquerdo = %b%b%b%b%b%b%b,Saida display direito = %b%b%b%b%b%b%b",
						a, b, c, d, dse_t[6], dse_t[5], dse_t[4], dse_t[3], dse_t[2], dse_t[1], dse_t[0],
						dsd_t[6],dsd_t[5],dsd_t[4],dsd_t[3],dsd_t[2],dsd_t[1],dsd_t[0]);

		
		// testando para entrada 7 saida 13
		reset = 1;
		#4;
		reset = 0;
		#4;
		
		a = 1'b0; b = 1'b1; c = 1'b1; d = 1'b1;
		#4;

		$display( "Entradas = %b%b%b%b, Saida display esquerdo = %b%b%b%b%b%b%b,Saida display direito = %b%b%b%b%b%b%b",
						a, b, c, d, dse_t[6], dse_t[5], dse_t[4], dse_t[3], dse_t[2], dse_t[1], dse_t[0],
						dsd_t[6],dsd_t[5],dsd_t[4],dsd_t[3],dsd_t[2],dsd_t[1],dsd_t[0]);

		
		// testando para entrada 8 saida 14
		reset = 1;
		#4;
		reset = 0;
		#4;
		
		a = 1'b1; b = 1'b0; c = 1'b0; d = 1'b0;
		#4;

		$display( "Entradas = %b%b%b%b, Saida display esquerdo = %b%b%b%b%b%b%b,Saida display direito = %b%b%b%b%b%b%b",
						a, b, c, d, dse_t[6], dse_t[5], dse_t[4], dse_t[3], dse_t[2], dse_t[1], dse_t[0],
						dsd_t[6],dsd_t[5],dsd_t[4],dsd_t[3],dsd_t[2],dsd_t[1],dsd_t[0]);

		
		
		// testando para entrada 9 saida 12
		reset = 1;
		#4;
		reset = 0;
		#4;
		
		a = 1'b1; b = 1'b0; c = 1'b0; d = 1'b1;
		#4;

		$display( "Entradas = %b%b%b%b, Saida display esquerdo = %b%b%b%b%b%b%b,Saida display direito = %b%b%b%b%b%b%b",
						a, b, c, d, dse_t[6], dse_t[5], dse_t[4], dse_t[3], dse_t[2], dse_t[1], dse_t[0],
						dsd_t[6],dsd_t[5],dsd_t[4],dsd_t[3],dsd_t[2],dsd_t[1],dsd_t[0]);

		
		// testando para entrada 10 saida 11
		reset = 1;
		#4;
		reset = 0;
		#4;
		
		a = 1'b1; b = 1'b0; c = 1'b1; d = 1'b0;
		#4;

		$display( "Entradas = %b%b%b%b, Saida display esquerdo = %b%b%b%b%b%b%b,Saida display direito = %b%b%b%b%b%b%b",
						a, b, c, d, dse_t[6], dse_t[5], dse_t[4], dse_t[3], dse_t[2], dse_t[1], dse_t[0],
						dsd_t[6],dsd_t[5],dsd_t[4],dsd_t[3],dsd_t[2],dsd_t[1],dsd_t[0]);

		
		// testando para entrada 11 saida 4
		reset = 1;
		#4;
		reset = 0;
		#4;
		
		a = 1'b1; b = 1'b0; c = 1'b1; d = 1'b1;
		#4;

		$display( "Entradas = %b%b%b%b, Saida display esquerdo = %b%b%b%b%b%b%b,Saida display direito = %b%b%b%b%b%b%b",
						a, b, c, d, dse_t[6], dse_t[5], dse_t[4], dse_t[3], dse_t[2], dse_t[1], dse_t[0],
						dsd_t[6],dsd_t[5],dsd_t[4],dsd_t[3],dsd_t[2],dsd_t[1],dsd_t[0]);

		
		
		
		// testando para entrada 12 saida 7
		reset = 1;
		#4;
		reset = 0;
		#4;
		
		a = 1'b1; b = 1'b1; c = 1'b0; d = 1'b0;
		#4;

		$display( "Entradas = %b%b%b%b, Saida display esquerdo = %b%b%b%b%b%b%b,Saida display direito = %b%b%b%b%b%b%b",
						a, b, c, d, dse_t[6], dse_t[5], dse_t[4], dse_t[3], dse_t[2], dse_t[1], dse_t[0],
						dsd_t[6],dsd_t[5],dsd_t[4],dsd_t[3],dsd_t[2],dsd_t[1],dsd_t[0]);

		
		// testando para entrada 13 saida 1
		reset = 1;
		#4;
		reset = 0;
		#4;
		
		a = 1'b1; b = 1'b1; c = 1'b0; d = 1'b1;
		#4;

		$display( "Entradas = %b%b%b%b, Saida display esquerdo = %b%b%b%b%b%b%b,Saida display direito = %b%b%b%b%b%b%b",
						a, b, c, d, dse_t[6], dse_t[5], dse_t[4], dse_t[3], dse_t[2], dse_t[1], dse_t[0],
						dsd_t[6],dsd_t[5],dsd_t[4],dsd_t[3],dsd_t[2],dsd_t[1],dsd_t[0]);

		
		// testando para entrada 14 saida 6
		reset = 1;
		#4;
		reset = 0;
		#4;
		
		a = 1'b1; b = 1'b1; c = 1'b1; d = 1'b0;
		#4;

		$display( "Entradas = %b%b%b%b, Saida display esquerdo = %b%b%b%b%b%b%b,Saida display direito = %b%b%b%b%b%b%b",
						a, b, c, d, dse_t[6], dse_t[5], dse_t[4], dse_t[3], dse_t[2], dse_t[1], dse_t[0],
						dsd_t[6],dsd_t[5],dsd_t[4],dsd_t[3],dsd_t[2],dsd_t[1],dsd_t[0]);

		
		// testando para entrada 15 saida 5
		reset = 1;
		#4;
		reset = 0;
		#4;
		
		a = 1'b1; b = 1'b1; c = 1'b1; d = 1'b1;
		#4;

		$display( "Entradas = %b%b%b%b, Saida display esquerdo = %b%b%b%b%b%b%b,Saida display direito = %b%b%b%b%b%b%b",
						a, b, c, d, dse_t[6], dse_t[5], dse_t[4], dse_t[3], dse_t[2], dse_t[1], dse_t[0],
						dsd_t[6],dsd_t[5],dsd_t[4],dsd_t[3],dsd_t[2],dsd_t[1],dsd_t[0]);
		

		$stop;
	end
endmodule

Códigos/simulation/modelsim/teste_gtk.vcd
$date
	Fri Oct 27 00:42:09 2023
$end
$version
	ModelSim Version 2020.1
$end
$timescale
	1ps
$end

$scope module TestBench $end
$var reg 1 ! a $end
$var reg 1 " b $end
$var reg 1 # c $end
$var reg 1 $ d $end
$var reg 1 % ready $end
$var reg 1 & reset $end
$var wire 1 ' dse_t [6] $end
$var wire 1 ( dse_t [5] $end
$var wire 1 ) dse_t [4] $end
$var wire 1 * dse_t [3] $end
$var wire 1 + dse_t [2] $end
$var wire 1 , dse_t [1] $end
$var wire 1 - dse_t [0] $end
$var wire 1 . dsd_t [6] $end
$var wire 1 / dsd_t [5] $end
$var wire 1 0 dsd_t [4] $end
$var wire 1 1 dsd_t [3] $end
$var wire 1 2 dsd_t [2] $end
$var wire 1 3 dsd_t [1] $end
$var wire 1 4 dsd_t [0] $end

$scope module tb $end
$var wire 1 5 a $end
$var wire 1 6 b $end
$var wire 1 7 c $end
$var wire 1 8 d $end
$var wire 1 9 ready $end
$var wire 1 : reset $end
$var wire 1 ; s0 $end
$var wire 1 < s1 $end
$var wire 1 = s2 $end
$var wire 1 > s3 $end
$var reg 7 ? dse [0:6] $end
$var reg 7 @ dsd [0:6] $end

$scope module en $end
$var wire 1 5 A $end
$var wire 1 6 B $end
$var wire 1 7 C $end
$var wire 1 8 D $end
$var wire 1 9 Ready $end
$var wire 1 : Reset $end
$var wire 1 ; S0 $end
$var wire 1 < S1 $end
$var wire 1 = S2 $end
$var wire 1 > S3 $end
$upscope $end
$upscope $end
$upscope $end
$enddefinitions $end
#0
$dumpvars
x!
x"
x#
x$
1%
1&
b1111110 ?
b1111110 @
0-
1,
1+
1*
1)
1(
1'
04
13
12
11
10
1/
1.
1;
1<
1=
1>
1:
19
x8
x7
x6
x5
$end
#10000
0&
0:
x>
x=
x<
x;
b1111111 @
b1111111 ?
1-
14
#20000
0!
0"
0#
0$
05
06
07
08
0=
1>
1<
0;
b1 @
b1001111 ?
0)
0(
03
02
01
00
0/
0.
#40000
1&
1:
1=
1;
b1111110 @
b1111110 ?
0-
1)
1(
04
13
12
11
10
1/
1.
#50000
0&
0:
0=
0;
b1 @
b1001111 ?
1-
0)
0(
14
03
02
01
00
0/
0.
#54000
1$
18
0>
1;
b110 @
b1111111 ?
1)
1(
04
13
12
#58000
1&
1:
1>
1=
b1111110 @
b1111110 ?
0-
11
10
1/
1.
#62000
0&
0:
0>
0=
b110 @
b1111111 ?
1-
01
00
0/
0.
#66000
1#
0$
17
08
0<
1>
b1100 @
03
11
#70000
1&
1:
1=
1<
b1111110 @
b1111110 ?
0-
13
10
1/
1.
#74000
0&
0:
0=
0<
b1100 @
b1111111 ?
1-
03
00
0/
0.
#78000
1$
18
0>
0;
b1 @
14
02
01
#82000
1&
1:
1>
1=
1<
1;
b1111110 @
b1111110 ?
0-
04
13
12
11
10
1/
1.
#86000
0&
0:
0>
0=
0<
0;
b1 @
b1111111 ?
1-
14
03
02
01
00
0/
0.
#90000
1"
0#
0$
16
07
08
1>
b0 @
04
#94000
1&
1:
1=
1<
1;
b1111110 @
b1111110 ?
0-
13
12
11
10
1/
1.
#98000
0&
0:
0=
0<
0;
b0 @
b1111111 ?
1-
03
02
01
00
0/
0.
#102000
1$
18
1=
1<
1;
b100100 @
b1001111 ?
0)
0(
12
1/
#106000
1&
1:
b1111110 @
b1111110 ?
0-
1)
1(
13
11
10
1.
#110000
0&
0:
b100100 @
b1001111 ?
1-
0)
0(
03
01
00
0.
#114000
1#
0$
17
08
0>
0=
0;
b10010 @
b1111111 ?
1)
1(
13
02
10
0/
#118000
1&
1:
1>
1=
1;
b1111110 @
b1111110 ?
0-
12
11
1/
1.
#122000
0&
0:
0>
0=
0;
b10010 @
b1111111 ?
1-
02
01
0/
0.
#126000
1$
18
1>
1=
0<
1;
b110 @
b1001111 ?
0)
0(
12
00
#130000
1&
1:
1<
b1111110 @
b1111110 ?
0-
1)
1(
11
10
1/
1.
#134000
0&
0:
0<
b110 @
b1001111 ?
1-
0)
0(
01
00
0/
0.
#138000
1!
0"
0#
0$
15
06
07
08
0;
1<
b1001100 @
03
11
1.
#142000
1&
1:
1;
b1111110 @
b1111110 ?
0-
1)
1(
13
10
1/
#146000
0&
0:
0;
b1001100 @
b1001111 ?
1-
0)
0(
03
00
0/
#150000
1$
18
0<
b10010 @
13
02
01
10
0.
#154000
1&
1:
1<
1;
b1111110 @
b1111110 ?
0-
1)
1(
12
11
1/
1.
#158000
0&
0:
0<
0;
b10010 @
b1001111 ?
1-
0)
0(
02
01
0/
0.
#162000
1#
0$
17
08
0=
1<
1;
b1001111 @
14
12
11
00
1.
#166000
1&
1:
1=
b1111110 @
b1111110 ?
0-
1)
1(
04
10
1/
#170000
0&
0:
0=
b1001111 @
b1001111 ?
1-
0)
0(
14
00
0/
#174000
1$
18
0>
1=
0<
0;
b1001100 @
b1111111 ?
1)
1(
04
03
#178000
1&
1:
1>
1<
1;
b1111110 @
b1111110 ?
0-
13
10
1/
#182000
0&
0:
0>
0<
0;
b1001100 @
b1111111 ?
1-
03
00
0/
#186000
1"
0#
0$
16
07
08
1;
1<
b1111 @
14
13
0.
#190000
1&
1:
1>
b1111110 @
b1111110 ?
0-
04
10
1/
1.
#194000
0&
0:
0>
b1111 @
b1111111 ?
1-
14
00
0/
0.
#198000
1$
18
0=
0<
b1001111 @
1.
#202000
1&
1:
1>
1=
1<
b1111110 @
b1111110 ?
0-
04
10
1/
#206000
0&
0:
0>
0=
0<
b1001111 @
b1111111 ?
1-
14
00
0/
#210000
1#
0$
17
08
1=
1<
0;
b100000 @
04
03
02
01
1/
0.
#214000
1&
1:
1>
1;
b1111110 @
b1111110 ?
0-
13
12
11
10
1.
#218000
0&
0:
0>
0;
b100000 @
b1111111 ?
1-
03
02
01
00
0.
#222000
1$
18
0<
1;
b100100 @
12
