TP2/Display.v
 module Display(
    input wire clk, reset, 
    input wire [1:0] premio_f,
    input wire [4:0] p1_f, p2_f,
    input wire [3:0] state_f,
    output reg [0:6] hex1, hex0, hex2, hex3,
    output reg [0:1] ledp1, ledp2,
    output reg led15,
    output reg sled,
	 output reg [3:0] gled
);

	 
	 parameter zero   = 7'b0000001,
              um     = 7'b1001111,
              dois   = 7'b0010010,
              tres   = 7'b0000110,
              quatro = 7'b1001100,
              cinco  = 7'b0100100,
              seis   = 7'b0100000,
              sete   = 7'b0001111,
              oito   = 7'b0000000,
              nove   = 7'b0000100,
              traco  = 7'b1111110, 
              apagado = 7'b0000000; 
     
    parameter s0 = 4'b0000,
              s1 = 4'b0001,
              s2 = 4'b0010,
              s3 = 4'b0011,
              s4 = 4'b0100,
              sg1 = 4'b0101, // estado de premio 1
              sg2 = 4'b0110, // estado de premio 2
              sg0 = 4'b0111, // estado de premio 0
              sgx = 4'b1000; // estado de espera 
	
	initial begin
        ledp1 = 2'b00;
        ledp2 = 2'b00;
        hex3 = traco;
        hex2 = traco;
        hex0 = traco;
        hex1 = traco;
    end
    
   
    always @(*) begin
        if (reset == 1'b1) begin
            ledp1 = 2'b00;
            ledp2 = 2'b00;
            hex3 = traco;
            hex2 = traco;
            hex0 = traco;
            hex1 = traco;
        end
        case (premio_f)
            2'b01:begin
                ledp1 = 2'b11;
                ledp2 = 2'b00;
                case (p1_f)
                    4'b0000:begin
                        hex1 = zero;
                        hex0 = zero;
                    end
                    4'b0001:begin
                        hex1 = zero;
                        hex0 = um;
                    end
                    4'b0010:begin
                        hex1 = zero;
                        hex0 = dois;
                    end
                    4'b0011:begin
                        hex1 = zero;
                        hex0 = tres;
                    end
                    4'b0100:begin
                        hex1 = zero;
                        hex0 = quatro;
                    end
                    4'b0101:begin
                        hex1 = zero;
                        hex0 = cinco;
                    end
                    4'b0110:begin
                        hex1 = zero;
                        hex0 = seis;
                    end
                    4'b0111:begin
                        hex1 = zero;
                        hex0 = sete;
                    end
                    4'b1000:begin
                        hex1 = zero;
                        hex0 = oito;
                    end
                    4'b1001:begin
                        hex1 = zero;
                        hex0 = nove;
                    end

       
                endcase
            end
            2'b10: begin
                ledp1 = 2'b00;
                ledp2 = 2'b11;
                case (p2_f)
                    4'b0000:begin
                        hex3 = zero;
                        hex2 = zero;
                        
                    end
                    4'b0001: begin
                        hex3 = zero;
                        hex2 = um;
                    end
                    4'b0010: begin
                        hex3 = zero;
                        hex2 = dois;
                    end
                    4'b0011: begin
                        hex3 = zero;
                        hex2 = tres;
                    end
                    4'b0100: begin
                        hex3 = zero;
                        hex2 = quatro;
                    end
                    4'b0101: begin
                        hex3 = zero;
                        hex2 = cinco;
                    end
                    4'b0110: begin
                        hex3 = zero;
                        hex2 = seis;
                    end
                    4'b0111: begin
                        hex3 = zero;
                        hex2 = sete;
                    end
                    4'b1000: begin
                        hex3 = zero;
                        hex2 = oito;
                    end
                    4'b1001: begin
                        hex3 = zero;
                        hex2 = nove;
                    end
                    
                endcase
            end
            2'b00: begin
                ledp1 = 2'b00;
                ledp2 = 2'b00;
            end  
        endcase
    end
	 
	always @(state_f) begin
			 gled <= state_f;
          if (state_f == s0) begin
            sled <= 1;
          end else begin
            sled <= ~sled;
          end
		  if(state_f == s4)begin
				led15 <= 1;
		  end else begin
				led15 <= 0;
		  end
    end
    
	 
endmodule

TP2/Lot.v
module Lot(clk, num, reset, fim, fim_jogo, insere, premio, p1, p2, state);
  input  clk, reset, fim, insere, fim_jogo; 
  input  [3:0] num;
  output reg [1:0] premio;
  output reg [4:0] p1, p2;
  output reg [3:0] state; // registrador de estados ps; mudei aqui
  reg [3:0] c;   // registrador de consecutivos
  
  // num da loteria: 47019
  /* Codificação dos premios:
		- premio 1 = 01
		- premio 2 = 10
		- s/premio = 00
  */
  parameter s0 = 4'b0000,
    s1  = 4'b0001,
    s2  = 4'b0010,
    s3  = 4'b0011,
    s4  = 4'b0100,
	 sg1 = 4'b0101, // estado de premio 1
	 sg2 = 4'b0110, // estado de premio 2
    sg0 = 4'b0111, // estado de premio 0
	 sgx = 4'b1000; // estado de espera 
					
  
  
  
  initial begin
    state <= s0;
    premio = 2'b00;
    p1 = 5'b00000;
    p2 = 5'b00000;
	 c = 4'b0000;
  end 
  
  always @(posedge clk , posedge reset , posedge fim_jogo , posedge fim) begin
    if (reset == 1'b1) begin
			state <= s0;
			premio <= 2'b00;
			p1 <= 5'b00000;
			p2 <= 5'b00000;
			c <= 4'b0000;
    end else if (fim_jogo == 1'b1) begin
			state <= s0;
			premio <= 2'b00;
			c <= 4'b0000;
    end else if (fim == 1'b1) begin //  depois de comprarar e os numeros de input com os numeros da loteria e gerar o estado de premio, e mostrado a saída e contabilizado o premio
        case(state)
			sg1: begin
				premio = 2'b01;
				p1 <= p1 + 1;
				state <= sgx;
			end
			sg2: begin
				premio = 2'b10;
				p2 <= p2 + 1;
				state <= sgx;
			end
            sg0: begin
                premio = 2'b00;
					 state <= sgx;
            end
				sgx: begin
					premio <= premio;
					state <= state;
				end
			default: begin
				premio = 2'b00;
				state <= state;
			end
		endcase
	 end else if(insere) begin // caso de inserção, onde o numero do input é comparado com os numero da loteria, caso seja iguais, é somado mais 1 no contador de consecutivo e pula para o próximo estado, caso contrario, só pula para o próximo estado;
			case (state)
                s0: begin
                    if(num == 4'b0100)begin
                        c <= c+1;
                        state <= s1;
                    end else if(num != 4'b0100 && num < 4'b1010)begin
                        c <= 0;
                        state <= s1;
                    end else if(num > 4'b1001)begin
								state <= sgx;
					end
						  
                end
                s1: begin
                    if(num == 4'b0111)begin
                        c <= c+1;
                        state <= s2;
                    end else if (num != 4'b0111 && num < 4'b1010) begin
                        c <= 0;
                        state <= s2;                       
                    end else if(num > 4'b1001)begin
								state <= sgx;
					end
                end
                s2: begin
                    if(num == 4'b0000)begin
                        c <= c+1;
                        state <= s3;
                    end else if(num != 4'b0000 && num < 4'b1010)begin
                        if (c >= 2) begin // caso o numero de consecutivo foi maior ou igual a 2, a pessoa tem a chance com o digito 5, por isso mesmo que erre, o contador nao pode zerar;
                            state <= s3;
                        end else if(num > 4'b1001 )begin
									state <= sgx;
					    end else begin
                            c <= 0;
                            state <= s3;
                        end
                        
                    end
                end
                s3: begin
                    if(num == 4'b0001)begin
                        if (c >= 3) begin
                            state <= sg1; // caso acerte os 4 numeros, vai direto para o estado de premio 1;
                        end else begin
                            c <= c +1;
                            state <= s4;  
                        end
                    end else if(num != 4'b0000 && num < 4'b1010)begin
                        if (c >= 2) begin
                            state <= s4;
                        end else if(num > 4'b1001)begin
									 state <= sgx;
					    end else begin
                            c <= 0;
                            state <= s4;
                        end
                    end
                end
                s4: begin
                   case (c) // analisando o contador,
                        2'b10: begin
                            if(insere && (num == 4'b1001))begin // se é dois consecutivos e acerta o digito 5, ganha o premio 2;
                                state <= sg2;
                            end else if(insere && (num != 4'b1001))begin
                                state <= sg0; // caso contrario não ganha nada;
                            end
                        end
                        2'b11: begin
                            if(insere &&(num == 4'b1001))begin // caso acerte 3 consecutivo e o digito 5, ganha o premio 1;
                                state <= sg1;
                            end else if(insere && (num != 4'b1001))begin
                                state <= sg2; // caso erre o 5, fica com 3 consecutivo e ganha o premio 2;
                            end
                        end
						default: begin
                            state <= sg0; 
                        end		
                    endcase 
                end 
            endcase
     end  
  end
endmodule

TP2/Top.v
module Top (
    input wire clk, fim, insere, fim_jogo, reset,
    input wire [3:0] num,
    output wire [0:6] hex0, hex1, hex2, hex3,
    output wire [0:1] ledp1, ledp2,
    output wire led15, sled,
    output wire [3:0] gled,
    output wire [3:0] state
);

    wire [1:0] premio;
    wire [4:0] p1, p2;

    Lot lt(
        .clk(clk), .num(num), .reset(reset),
        .fim(fim), .fim_jogo(fim_jogo),
        .insere(insere), .premio(premio),
        .p1(p1), .p2(p2), .state(state)
    );

    Display ds(
        .hex0(hex0), .hex1(hex1), .hex2(hex2), .hex3(hex3),
        .ledp1(ledp1), .ledp2(ledp2), .led15(led15),
        .premio_f(premio), .p1_f(p1), .p2_f(p2),
        .state_f(state), .sled(sled), .gled(gled), .reset(reset)
    );

endmodule

TP2/lot_tb.v
`timescale 1ns / 1ps

module lot_tb;

  reg clk,reset, fim, insere, fim_jogo;
  reg [3:0] num;
  wire [0:6] hex1, hex0, hex2, hex3;
  wire [0:1] ledp1, ledp2;
  wire led15, sled;
  wire [3:0] state, gled;
  
  
  
  // Instanciação do módulo Top
  Top uut (
    .clk(clk),
    .num(num),
    .reset(reset),
    .fim(fim),
    .fim_jogo(fim_jogo),
    .insere(insere),
    .hex1(hex1),
    .hex0(hex0),
    .hex2(hex2),
    .hex3(hex3),
    .ledp1(ledp1),
    .ledp2(ledp2),
    .led15(led15),
    .state(state),
    .sled(sled),
	 .gled(gled)
  );

 
    /*
    Numeros para teste:
    47010 - premio 1 - 4 consecutivos
    67039 - premio 2 - 2 consequtivos + acerto 5o digito;
    47029 - premio 1 - 3 consequitivos + acerto 5o digito;
    23119 - premio 0 - 1 consequtivo + acerto 5o digito;
    49219 - premio 0 - 2 num, mas não consequtivos + acerto 5o digito;
    17011 - prmeio 0 - 3 consecutivos + erro 5o digito;
    */

  initial begin
    $dumpfile("teste_tp2_gtk.vcd");
	 $dumpvars;
    clk = 0;
    reset = 1;
    insere = 0;
    fim = 0;
    fim_jogo = 0;
    #10
    reset = 0;
    #10

    insere = 1;
    num = 4'b0100; #10 num = 4'b0111; #10 num = 4'b0000; #10 num = 4'b0001; #10 num = 4'b0000; // 47010 
    #10
    insere = 0;
    fim = 1;
    #10
    fim = 0;
    $display("Premio sorteado: %d, Quantidade de P1: %d, Quantidade de P2: %d", uut.premio, uut.p1, uut.p2);
    fim_jogo = 1;
    #10
    fim_jogo = 0;
    #10
    insere = 1;

    num = 4'b0110; #10 num = 4'b0111; #10 num = 4'b0000; #10 num = 4'b0011; #10 num = 4'b1001; // 67039
    #10
    insere = 0;
    #10
    fim = 1;
    #10
    fim = 0;
    $display("Premio sorteado: %d, Quantidade de P1: %d, Quantidade de P2: %d", uut.premio, uut.p1, uut.p2);
    fim_jogo = 1;
    #10

    fim_jogo = 0;
    #10
    insere = 1;
    num = 4'b0100; #10 num = 4'b0111; #10 num = 4'b0000; #10 num = 4'b0010; #10 num = 4'b1001; 
    #10
    insere = 0;
    #10
    fim = 1;
    #10
    fim = 0;
    $display("Premio sorteado: %d, Quantidade de P1: %d, Quantidade de P2: %d", uut.premio, uut.p1, uut.p2);
    fim_jogo = 1;
    #10
    fim_jogo = 0;
    #10

    insere = 1;
    num = 4'b0010; #10 num = 4'b0011; #10 num = 4'b0001; #10 num = 4'b0001; #10 num = 4'b1001; // 49219
    #10
    insere = 0;
    #10
    fim = 1;
    #10
    fim = 0;
    $display("Premio sorteado: %d, Quantidade de P1: %d, Quantidade de P2: %d", uut.premio, uut.p1, uut.p2);
    fim_jogo = 1;
    #10
    fim_jogo = 0;
    #10

    insere = 1;
    num = 4'b0010; #10 num = 4'b0011; #10 num = 4'b0001; #10 num = 4'b0001; #10 num = 4'b1001; // 23119
    #10
    insere = 0;
    #10
    fim = 1;
    #10
    fim = 0;
    $display("Premio sorteado: %d, Quantidade de P1: %d, Quantidade de P2: %d", uut.premio, uut.p1, uut.p2);
    fim_jogo = 1;
    #10
    fim_jogo = 0;
    #10
    
    insere = 1;
    num = 4'b0001; #10 num = 4'b0111; #10 num = 4'b0000; #10 num = 4'b0001; #10 num = 4'b0001; // 17011
    #10
    insere = 0;
    #10
    fim = 1;
    #10
    fim = 0;
    $display("Premio sorteado: %d, Quantidade de P1: %d, Quantidade de P2: %d", uut.premio, uut.p1, uut.p2);
    fim_jogo = 1;
    #10

	  reset = 1;

    $stop;
  end
  always #5 clk = ~clk;

endmodule

TP2/teste_tp2_gtk.vcd
$date
	Thu Dec  7 02:08:20 2023
$end
$version
	Icarus Verilog
$end
$timescale
	1ps
$end
$scope module lot_tb $end
$var wire 4 ! state [3:0] $end
$var wire 1 " sled $end
$var wire 2 # ledp2 [0:1] $end
$var wire 2 $ ledp1 [0:1] $end
$var wire 1 % led15 $end
$var wire 7 & hex3 [0:6] $end
$var wire 7 ' hex2 [0:6] $end
$var wire 7 ( hex1 [0:6] $end
$var wire 7 ) hex0 [0:6] $end
$var wire 4 * gled [3:0] $end
$var reg 1 + clk $end
$var reg 1 , fim $end
$var reg 1 - fim_jogo $end
$var reg 1 . insere $end
$var reg 4 / num [3:0] $end
$var reg 1 0 reset $end
$scope module uut $end
$var wire 1 + clk $end
$var wire 1 , fim $end
$var wire 1 - fim_jogo $end
$var wire 1 . insere $end
$var wire 4 1 num [3:0] $end
$var wire 1 0 reset $end
$var wire 4 2 state [3:0] $end
$var wire 1 " sled $end
$var wire 2 3 premio [1:0] $end
$var wire 5 4 p2 [4:0] $end
$var wire 5 5 p1 [4:0] $end
$var wire 2 6 ledp2 [0:1] $end
$var wire 2 7 ledp1 [0:1] $end
$var wire 1 % led15 $end
$var wire 7 8 hex3 [0:6] $end
$var wire 7 9 hex2 [0:6] $end
$var wire 7 : hex1 [0:6] $end
$var wire 7 ; hex0 [0:6] $end
$var wire 4 < gled [3:0] $end
$scope module ds $end
$var wire 1 = clk $end
$var wire 1 0 reset $end
$var wire 4 > state_f [3:0] $end
$var wire 2 ? premio_f [1:0] $end
$var wire 5 @ p2_f [4:0] $end
$var wire 5 A p1_f [4:0] $end
$var parameter 7 B apagado $end
$var parameter 7 C cinco $end
$var parameter 7 D dois $end
$var parameter 7 E nove $end
$var parameter 7 F oito $end
$var parameter 7 G quatro $end
$var parameter 4 H s0 $end
$var parameter 4 I s1 $end
$var parameter 4 J s2 $end
$var parameter 4 K s3 $end
$var parameter 4 L s4 $end
$var parameter 7 M seis $end
$var parameter 7 N sete $end
$var parameter 4 O sg0 $end
$var parameter 4 P sg1 $end
$var parameter 4 Q sg2 $end
$var parameter 4 R sgx $end
$var parameter 7 S traco $end
$var parameter 7 T tres $end
$var parameter 7 U um $end
$var parameter 7 V zero $end
$var reg 4 W gled [3:0] $end
$var reg 7 X hex0 [0:6] $end
$var reg 7 Y hex1 [0:6] $end
$var reg 7 Z hex2 [0:6] $end
$var reg 7 [ hex3 [0:6] $end
$var reg 1 % led15 $end
$var reg 2 \ ledp1 [0:1] $end
$var reg 2 ] ledp2 [0:1] $end
$var reg 1 " sled $end
$upscope $end
$scope module lt $end
$var wire 1 + clk $end
$var wire 1 , fim $end
$var wire 1 - fim_jogo $end
$var wire 1 . insere $end
$var wire 4 ^ num [3:0] $end
$var wire 1 0 reset $end
$var parameter 4 _ s0 $end
$var parameter 4 ` s1 $end
$var parameter 4 a s2 $end
$var parameter 4 b s3 $end
$var parameter 4 c s4 $end
$var parameter 4 d sg0 $end
$var parameter 4 e sg1 $end
$var parameter 4 f sg2 $end
$var parameter 4 g sgx $end
$var reg 4 h c [3:0] $end
$var reg 5 i p1 [4:0] $end
$var reg 5 j p2 [4:0] $end
$var reg 2 k premio [1:0] $end
$var reg 4 l state [3:0] $end
$upscope $end
$upscope $end
$upscope $end
$enddefinitions $end
$comment Show the parameter values. $end
$dumpall
b1000 g
b110 f
b101 e
b111 d
b100 c
b11 b
b10 a
b1 `
b0 _
b1 V
b1001111 U
b110 T
b1111110 S
b1000 R
b110 Q
b101 P
b111 O
b1111 N
b100000 M
b100 L
b11 K
b10 J
b1 I
b0 H
b1001100 G
b0 F
b100 E
b10010 D
b100100 C
b0 B
$end
#0
$dumpvars
b0 l
b0 k
b0 j
b0 i
b0 h
bx ^
b0 ]
b0 \
b1111110 [
b1111110 Z
b1111110 Y
b1111110 X
b0 W
b0 A
b0 @
b0 ?
b0 >
z=
b0 <
b1111110 ;
b1111110 :
b1111110 9
b1111110 8
b0 7
b0 6
b0 5
b0 4
b0 3
b0 2
bx 1
10
bx /
0.
0-
0,
0+
b0 *
b1111110 )
b1111110 (
b1111110 '
b1111110 &
0%
b0 $
b0 #
1"
b0 !
$end
#5000
1+
#10000
0+
00
#15000
1+
#20000
0+
b100 /
b100 1
b100 ^
1.
#25000
0"
b1 *
b1 <
b1 W
b1 !
b1 2
b1 >
b1 l
b1 h
1+
#30000
0+
b111 /
b111 1
b111 ^
#35000
1"
b10 *
b10 <
b10 W
b10 !
b10 2
b10 >
b10 l
b10 h
1+
#40000
0+
b0 /
b0 1
b0 ^
#45000
0"
b11 *
b11 <
b11 W
b11 !
b11 2
b11 >
b11 l
b11 h
1+
#50000
0+
b1 /
b1 1
b1 ^
#55000
1"
b101 *
b101 <
b101 W
b101 !
b101 2
b101 >
b101 l
1+
#60000
0+
b0 /
b0 1
b0 ^
#65000
1+
#70000
0"
b1000 *
b1000 <
b1000 W
b1000 !
b1000 2
b1000 >
b1000 l
b1 5
b1 A
b1 i
b1001111 )
b1001111 ;
b1001111 X
b1 (
b1 :
b1 Y
b11 $
b11 7
b11 \
b1 3
b1 ?
b1 k
0+
1,
0.
#75000
1+
#80000
1"
b0 *
b0 <
b0 W
b0 $
b0 7
b0 \
b0 h
b0 3
b0 ?
b0 k
b0 !
b0 2
b0 >
b0 l
0+
1-
0,
#85000
1+
#90000
0+
0-
#95000
1+
#100000
0+
b110 /
b110 1
b110 ^
1.
#105000
0"
b1 *
b1 <
b1 W
b1 !
b1 2
b1 >
b1 l
1+
#110000
0+
b111 /
b111 1
b111 ^
#115000
1"
b10 *
b10 <
b10 W
b10 !
b10 2
b10 >
b10 l
b1 h
1+
#120000
0+
b0 /
b0 1
b0 ^
#125000
0"
b11 *
b11 <
b11 W
b11 !
b11 2
b11 >
b11 l
b10 h
1+
#130000
0+
b11 /
b11 1
b11 ^
#135000
1%
1"
b100 *
b100 <
b100 W
b100 !
b100 2
b100 >
b100 l
1+
#140000
0+
b1001 /
b1001 1
b1001 ^
#145000
0%
0"
b110 *
b110 <
b110 W
b110 !
b110 2
b110 >
b110 l
1+
#150000
0+
0.
#155000
1+
#160000
1"
b1000 *
b1000 <
b1000 W
b1000 !
b1000 2
b1000 >
b1000 l
b1 4
b1 @
b1 j
b1001111 '
b1001111 9
b1001111 Z
b1 &
b1 8
b1 [
b11 #
b11 6
b11 ]
b10 3
b10 ?
b10 k
0+
1,
#165000
1+
#170000
b0 *
b0 <
b0 W
b0 #
b0 6
b0 ]
b0 h
b0 3
b0 ?
b0 k
b0 !
b0 2
b0 >
b0 l
0+
1-
0,
#175000
1+
#180000
0+
0-
#185000
1+
#190000
0+
b100 /
b100 1
b100 ^
1.
#195000
0"
b1 *
b1 <
b1 W
b1 !
b1 2
b1 >
b1 l
b1 h
1+
#200000
0+
b111 /
b111 1
b111 ^
#205000
1"
b10 *
b10 <
b10 W
b10 !
b10 2
b10 >
b10 l
b10 h
1+
#210000
0+
b0 /
b0 1
b0 ^
#215000
0"
b11 *
b11 <
b11 W
b11 !
b11 2
b11 >
b11 l
b11 h
1+
#220000
0+
b10 /
b10 1
b10 ^
#225000
1%
1"
b100 *
b100 <
b100 W
b100 !
b100 2
b100 >
b100 l
1+
#230000
0+
b1001 /
b1001 1
b1001 ^
#235000
0%
0"
b101 *
b101 <
b101 W
b101 !
b101 2
b101 >
b101 l
1+
#240000
0+
0.
#245000
1+
#250000
1"
b1000 *
b1000 <
b1000 W
b10010 )
b10010 ;
b10010 X
b1000 !
b1000 2
b1000 >
b1000 l
b10 5
b10 A
b10 i
b11 $
b11 7
b11 \
b1 3
b1 ?
b1 k
0+
1,
#255000
1+
#260000
b0 *
b0 <
b0 W
b0 $
b0 7
b0 \
b0 h
b0 3
b0 ?
b0 k
b0 !
b0 2
b0 >
b0 l
0+
1-
0,
#265000
1+
#270000
0+
0-
#275000
1+
#280000
0+
b10 /
b10 1
b10 ^
1.
#285000
0"
b1 *
b1 <
b1 W
b1 !
b1 2
b1 >
b1 l
1+
#290000
0+
b11 /
b11 1
b11 ^
#295000
1"
b10 *
b10 <
b10 W
b10 !
b10 2
b10 >
b10 l
1+
#300000
0+
b1 /
b1 1
b1 ^
#305000
0"
b11 *
b11 <
b11 W
b11 !
b11 2
b11 >
b11 l
1+
#310000
0+
#315000
1%
1"
b100 *
b100 <
b100 W
b100 !
b100 2
b100 >
b100 l
b1 h
1+
#320000
0+
b1001 /
b1001 1
b1001 ^
#325000
0%
0"
b111 *
b111 <
b111 W
b111 !
b111 2
b111 >
b111 l
1+
#330000
0+
0.
#335000
1+
#340000
1"
b1000 *
b1000 <
b1000 W
b1000 !
b1000 2
b1000 >
b1000 l
0+
1,
#345000
1+
#350000
b0 *
b0 <
b0 W
b0 h
b0 !
b0 2
b0 >
b0 l
0+
1-
0,
#355000
1+
#360000
0+
0-
#365000
1+
#370000
0+
b10 /
b10 1
b10 ^
1.
#375000
0"
b1 *
b1 <
b1 W
b1 !
b1 2
b1 >
b1 l
1+
#380000
0+
b11 /
b11 1
b11 ^
#385000
1"
b10 *
b10 <
b10 W
b10 !
b10 2
b10 >
b10 l
1+
#390000
0+
b1 /
b1 1
b1 ^
#395000
0"
b11 *
b11 <
b11 W
b11 !
b11 2
b11 >
b11 l
1+
#400000
0+
#405000
1%
1"
b100 *
b100 <
b100 W
b100 !
b100 2
b100 >
b100 l
b1 h
1+
#410000
0+
b1001 /
b1001 1
b1001 ^
#415000
0%
0"
b111 *
b111 <
b111 W
b111 !
b111 2
b111 >
b111 l
1+
#420000
0+
0.
#425000
1+
#430000
1"
b1000 *
b1000 <
b1000 W
b1000 !
b1000 2
b1000 >
b1000 l
0+
1,
#435000
1+
#440000
b0 *
b0 <
b0 W
b0 h
b0 !
b0 2
b0 >
b0 l
0+
1-
0,
#445000
1+
#450000
0+
0-
#455000
1+
#460000
0+
b1 /
b1 1
b1 ^
1.
#465000
0"
b1 *
b1 <
b1 W
b1 !
b1 2
b1 >
b1 l
1+
#470000
0+
b111 /
b111 1
b111 ^
#475000
1"
b10 *
b10 <
b10 W
b10 !
b10 2
b10 >
b10 l
b1 h
1+
#480000
0+
b0 /
b0 1
b0 ^
#485000
0"
b11 *
b11 <
b11 W
b11 !
b11 2
b11 >
b11 l
b10 h
1+
#490000
0+
b1 /
b1 1
b1 ^
#495000
1%
1"
b100 *
b100 <
b100 W
b100 !
b100 2
b100 >
b100 l
b11 h
1+
#500000
0+
#505000
0%
0"
b111 *
b111 <
b111 W
b111 !
b111 2
b111 >
b111 l
1+
#510000
0+
0.
#515000
1+
#520000
1"
b1000 *
b1000 <
b1000 W
b1000 !
b1000 2
b1000 >
b1000 l
0+
1,
#525000
1+
#530000
b0 *
b0 <
b0 W
b0 h
b0 !
b0 2
b0 >
b0 l
0+
1-
0,
