Codigos2.0/Codificador.v
/*
Declaração do Modulo
Codificador
*/

module Codificador (A, B, C, D, ready, reset, S0, S1, S2, S3);

  // Definir as entradas de 4 bits:
  input wire A;
  input wire B;
  input wire C;
  input wire D;
  input wire ready;
  input wire reset;

  // Definir as saídas:
  output reg S0;
  output reg S1;
  output reg S2;
  output reg S3;

  always @(posedge ready or posedge reset) begin
    if (reset) begin
      S0 <= 1'bx;
      S1 <= 1'bx;
      S2 <= 1'bx;
      S3 <= 1'bx;
    end else begin
      // Definição das expressões booleanas reduzidas via k-map:
      S0 <= (~A & ~C & D) | (~B & C & ~D) | (B & D) | (A & B & ~C);
      // Função do 1º bit descrita por A'C'D + B'CD' + BD + ABC'

      S1 <= (~A & ~B & ~C) | (~A & ~C & D) | (B & C & ~D) | (A & ~D);
      // Função do 2º bit descrita por A'B'C' + A'C'D + BCD' + AD

      S2 <= (~A & B & D) | (A & ~B & ~C) | (A & C & D) | (A & B & ~D);
      // Função do 3º bit descrita por A'BD + AB'C' + BCD + AB'D

      S3 <= (~A & ~C & ~D) | (~B & ~D) | (~A & B & D) | (A & ~B & ~C);
      // Função do 4º bit descrita por A'C'D' + B'D' + A'BD + AB'C'
    end
  end
endmodule

Codigos2.0/TesteBench.v
`timescale 1ns/100ps

module TesteBench();
	reg a, b, c, d, ready, reset;
	wire s0, s1, s2, s3;
	reg clk; // Adicione uma entrada de clock

	Codificador tb(.A(a), .B(b), .C(c), .D(d), .ready(ready), .reset(reset), .S0(s0), .S1(s1), .S2(s2), .S3(s3));
	
	initial begin
		// Inicialização das variáveis
		// 0;
		a = 0;
		b = 0;
		c = 0;
		d = 0;
		ready = 1;
		
		// Gerar um pulso de clock a cada 5 unidades de tempo
		//#5 clk = ~clk;
		
		
		
		// Testando para cada numero
		// 1;
		#1;
		reset = 1;
		ready = 0;
		#1;
		reset = 0;
		a = 0; b = 0; c = 0; d = 1;
		ready = 1;
		#1;
		
		// 2;
		#1;
		reset = 1;
		ready = 0;
		#1;
		reset = 0;
		a = 0; b = 0; c = 1; d = 0;
		ready = 1;
		#1
		
		// 3;
		#1;
		reset = 1;
		ready = 0;
		#1;
		reset = 0;
		a = 0; b = 0; c = 1; d = 1;
		ready = 1;
		#1
		
		// 4;
		#1;
		reset = 1;
		ready = 0;
		#1;
		reset = 0;
		a = 0; b = 1; c = 0; d = 0;
		ready = 1;
		#1
		
		// 5;
		#1;
		reset = 1;
		ready = 0;
		#1;
		reset = 0;
		a = 0; b = 1; c = 0; d = 1;
		ready = 1;
		#1
		
		// 6;
		#1;
		reset = 1;
		ready = 0;
		#1;
		reset = 0;
		a = 0; b = 1; c = 1; d = 0;
		ready = 1;
		#1
		
		// 7;
		#1;
		reset = 1;
		ready = 0;
		#1;
		reset = 0;
		a = 0; b = 1; c = 1; d = 1;
		ready = 1;
		#1
		
		// 8;
		#1;
		reset = 1;
		ready = 0;
		#1;
		reset = 0;
		a = 1; b = 0; c = 0; d = 0;
		ready = 1;
		#1
		
		// 9;
		#1;
		reset = 1;
		ready = 0;
		#1;
		reset = 0;
		a = 1; b = 0; c = 0; d = 1;
		ready = 1;
		#1
		
		// 10;
		#1;
		reset = 1;
		ready = 0;
		#1;
		reset = 0;
		a = 1; b = 0; c = 1; d = 0;
		ready = 1;
		#1
		
		// 11;
		#1;
		reset = 1;
		ready = 0;
		#1;
		reset = 0;
		a = 1; b = 0; c = 1; d = 1;
		ready = 1;
		#1
		
		// 12;
		#1;
		reset = 1;
		ready = 0;
		#1;
		reset = 0;
		a = 1; b = 1; c = 0; d = 0;
		ready = 1;
		#1
		
		// 13;
		#1;
		reset = 1;
		ready = 0;
		#1;
		reset = 0;
		a = 1; b = 1; c = 0; d = 1;
		ready = 1;
		#1
		
		// 14;
		#1;
		reset = 1;
		ready = 0;
		#1;
		reset = 0;
		a = 1; b = 1; c = 1; d = 0;
		ready = 1;
		#1
		
		// 15;
		#1;
		reset = 1;
		ready = 0;
		#1;
		reset = 0;
		a = 1; b = 1; c = 1; d = 1;
		ready = 1;
		#1
		
		$dumpfile("teste_gtk.vcd");
      $dumpvars;
		
		// Finalizar a simulação
		$stop;
	end
endmodule

Codigos2.0/teste_gtk.vcd
$date
	Sun Oct 08 17:31:11 2023
$end
$version
	ModelSim Version 2020.1
$end
$timescale
	1ps
$end
$scope module TesteBench $end
$var wire 1 ! s2 $end
$upscope $end
$enddefinitions $end
#0
0!
0!
#1000
x!
#2000
0!
#4000
x!
#5000
0!
#7000
x!
#8000
0!
#10000
x!
#11000
0!
#13000
x!
#14000
1!
#16000
x!
#17000
0!
#19000
x!
#20000
1!
#22000
x!
#23000
1!
#25000
x!
#26000
1!
#28000
x!
#29000
0!
#31000
x!
#32000
1!
#34000
x!
#35000
1!
#37000
x!
#38000
0!
#40000
x!
#41000
1!
#43000
x!
#44000
1!
